src/NTT/addr_gen.v
module addr_gen(
    input clk,
    input rst,
    input [1:0]mode,
    input [7:0]clk_counter,
    output [6:0]coef_addr,
    output [4:0]r_addr,
    output [4:0]w_addr
);
`define NTT 2'd0
`define INVNTT 2'd1
`define MULT 2'd2
//coef address
reg [7:0] coef_addr_reg;
wire [7:0] clk_counter_reg;
assign clk_counter_reg = clk_counter + 2;
always@(*) begin
    case (mode)
        `NTT:begin
           if(clk_counter[7:5] == 3'd6)begin
                coef_addr_reg = 7'd64 + (clk_counter[4:0] << 1);
            end
            else begin
                coef_addr_reg = (1 << clk_counter[7:5]) + (clk_counter[4:0] >> (3'd5 - clk_counter[7:5]));
            end
        end
        `INVNTT:begin
            if(clk_counter[7:5] == 3'b0)begin
                coef_addr_reg = 7'd126 - (clk_counter[4:0] << 1);
            end
            else begin
                if(clk_counter[7:5] == 3'd6)begin
                    coef_addr_reg = 1;
                end
                else begin
                    coef_addr_reg = (1 << (3'd7 - clk_counter[7:5])) - 1 - ((clk_counter[4:0] >> clk_counter[7:5])<<1) - clk_counter[0];
                end
            end
        end
        `MULT:begin
            if(clk_counter[7:1] >= 65) coef_addr_reg = 0;
            else begin
                coef_addr_reg = 8'd62 + {clk_counter_reg[7:2],1'b0}; 
            end
        end
        default:begin
            coef_addr_reg = 0;
        end 
    endcase
end
assign coef_addr = coef_addr_reg;
//read data address
reg [4:0] left_bits_raddr;
reg [4:0] right_bits_raddr;
wire [5:0] r_addr_wire;
reg [4:0] w_addr_regs[0:5];
always@(*) begin
    case(mode)
    `NTT: begin
        if(clk_counter[7:5] == 3'd5 || clk_counter[7:5] == 3'd6)begin
            left_bits_raddr = 0;
            right_bits_raddr = clk_counter[4:0];
        end
        else begin
            left_bits_raddr = {clk_counter[4:1] >> (3'd4 - clk_counter[7:5]), clk_counter[0]} << (4 - clk_counter[7:5]);
            right_bits_raddr = clk_counter[4:1] & ((1 << (4 - clk_counter[7:5])) - 1);
        end   
    end
    `INVNTT: begin
        if(clk_counter[7:5] == 3'd0 || clk_counter[7:5] == 3'd6) begin
            left_bits_raddr = 0;
            right_bits_raddr = clk_counter[4:0];
        end
        else begin
            left_bits_raddr = {clk_counter[4:1] >> (clk_counter[7:5] - 1), clk_counter[0]} << (clk_counter[7:5] - 1);
            right_bits_raddr = clk_counter[4:1] & ((1 << (clk_counter[7:5] - 1)) - 1);
        end
    end
    default: begin
        left_bits_raddr = 0;
        right_bits_raddr = 0;
    end
    endcase
end
assign r_addr_wire = left_bits_raddr + right_bits_raddr;
assign r_addr = r_addr_wire[4:0];
//write data address
always@(posedge clk or posedge rst)begin
    if(rst) begin
        w_addr_regs[0] <= 0;
        w_addr_regs[1] <= 0;
        w_addr_regs[2] <= 0;
        w_addr_regs[3] <= 0;
        w_addr_regs[4] <= 0;
        w_addr_regs[5] <= 0;
    end
    begin
        w_addr_regs[0] <= r_addr_wire[4:0];
        w_addr_regs[1] <= w_addr_regs[0];
        w_addr_regs[2] <= w_addr_regs[1];
        w_addr_regs[3] <= w_addr_regs[2];
        w_addr_regs[4] <= w_addr_regs[3];
        w_addr_regs[5] <= w_addr_regs[4];
    end
    
end
assign w_addr = mode == `MULT? clk_counter[7:2] - 3 : w_addr_regs[5];
endmodule

src/all_in_one/add_gen_tb.v
`include "addr_gen.v"

module bu_tb;
reg clk;
reg rst;
reg [1:0] mode; // 0:NTT, 1:INVNTT, 2:MULT, 3:ADDSUB
reg [7:0]clk_cnt;
wire [6:0]coef_addr;
wire [4:0]r_addr;
wire [4:0]w_addr;
addr_gen ADDR(
    .clk(clk),
    .mode(mode),
    .clk_counter(clk_cnt),
    .coef_addr(coef_addr),
    .r_addr(r_addr),
    .w_addr(w_addr)
    );
initial begin
    $dumpfile("addr_tb_1.vcd");
    $dumpvars(0, ADDR);
    #0
    rst = 1;
    mode = 1; // 0:NTT, 1:INVNTT, 2:MULT
    #1
    rst = 0;
    #456 
    $finish;
end
initial begin
    clk = 1;
    clk_cnt = 0;
    forever begin
        #1 
        clk = ~clk;
        if (clk) clk_cnt = clk_cnt + 1;
        if(clk_cnt[7:5] >= 7 || rst == 1) clk_cnt = 0;
    end
end
endmodule

src/NTT/addr_tb.vcd
$date
	Sun Jan 19 15:14:39 2025
$end
$version
	Icarus Verilog
$end
$timescale
	1s
$end
$scope module bu_tb $end
$scope module ADDR $end
$var wire 1 ! clk $end
$var wire 8 " clk_counter [7:0] $end
$var wire 2 # mode [1:0] $end
$var wire 1 $ rst $end
$var wire 5 % w_addr [4:0] $end
$var wire 6 & r_addr_wire [5:0] $end
$var wire 5 ' r_addr [4:0] $end
$var wire 7 ( coef_addr [6:0] $end
$var wire 8 ) clk_counter_reg [7:0] $end
$var reg 8 * coef_addr_reg [7:0] $end
$var reg 5 + left_bits_raddr [4:0] $end
$var reg 5 , right_bits_raddr [4:0] $end
$upscope $end
$upscope $end
$enddefinitions $end
$comment Show the parameter values. $end
$dumpall
$end
#0
$dumpvars
b0 ,
b0 +
b1111110 *
b10 )
b1111110 (
b0 '
b0 &
bx %
z$
b1 #
b0 "
1!
$end
#1
0!
#2
b1 '
b1111100 (
b1 &
b1 ,
b1111100 *
b11 )
b1 "
1!
#3
0!
#4
b10 '
b1111010 (
b10 &
b10 ,
b1111010 *
b100 )
b10 "
1!
#5
0!
#6
b11 '
b1111000 (
b11 &
b11 ,
b1111000 *
b101 )
b11 "
1!
#7
0!
#8
b100 '
b1110110 (
b100 &
b100 ,
b1110110 *
b110 )
b100 "
1!
#9
0!
#10
b101 '
b1110100 (
b101 &
b101 ,
b1110100 *
b111 )
b101 "
1!
#11
0!
#12
b0 %
b110 '
b1110010 (
b110 &
b110 ,
b1110010 *
b1000 )
b110 "
1!
#13
0!
#14
b1 %
b111 '
b1110000 (
b111 &
b111 ,
b1110000 *
b1001 )
b111 "
1!
#15
0!
#16
b10 %
b1000 '
b1101110 (
b1000 &
b1000 ,
b1101110 *
b1010 )
b1000 "
1!
#17
0!
#18
b11 %
b1001 '
b1101100 (
b1001 &
b1001 ,
b1101100 *
b1011 )
b1001 "
1!
#19
0!
#20
b100 %
b1010 '
b1101010 (
b1010 &
b1010 ,
b1101010 *
b1100 )
b1010 "
1!
#21
0!
#22
b101 %
b1011 '
b1101000 (
b1011 &
b1011 ,
b1101000 *
b1101 )
b1011 "
1!
#23
0!
#24
b110 %
b1100 '
b1100110 (
b1100 &
b1100 ,
b1100110 *
b1110 )
b1100 "
1!
#25
0!
#26
b111 %
b1101 '
b1100100 (
b1101 &
b1101 ,
b1100100 *
b1111 )
b1101 "
1!
#27
0!
#28
b1000 %
b1110 '
b1100010 (
b1110 &
b1110 ,
b1100010 *
b10000 )
b1110 "
1!
#29
0!
#30
b1001 %
b1111 '
b1100000 (
b1111 &
b1111 ,
b1100000 *
b10001 )
b1111 "
1!
#31
0!
#32
b1010 %
b10000 '
b1011110 (
b10000 &
b10000 ,
b1011110 *
b10010 )
b10000 "
1!
#33
0!
#34
b1011 %
b10001 '
b1011100 (
b10001 &
b10001 ,
b1011100 *
b10011 )
b10001 "
1!
#35
0!
#36
b1100 %
b10010 '
b1011010 (
b10010 &
b10010 ,
b1011010 *
b10100 )
b10010 "
1!
#37
0!
#38
b1101 %
b10011 '
b1011000 (
b10011 &
b10011 ,
b1011000 *
b10101 )
b10011 "
1!
#39
0!
#40
b1110 %
b10100 '
b1010110 (
b10100 &
b10100 ,
b1010110 *
b10110 )
b10100 "
1!
#41
0!
#42
b1111 %
b10101 '
b1010100 (
b10101 &
b10101 ,
b1010100 *
b10111 )
b10101 "
1!
#43
0!
#44
b10000 %
b10110 '
b1010010 (
b10110 &
b10110 ,
b1010010 *
b11000 )
b10110 "
1!
#45
0!
#46
b10001 %
b10111 '
b1010000 (
b10111 &
b10111 ,
b1010000 *
b11001 )
b10111 "
1!
#47
0!
#48
b10010 %
b11000 '
b1001110 (
b11000 &
b11000 ,
b1001110 *
b11010 )
b11000 "
1!
#49
0!
#50
b10011 %
b11001 '
b1001100 (
b11001 &
b11001 ,
b1001100 *
b11011 )
b11001 "
1!
#51
0!
#52
b10100 %
b11010 '
b1001010 (
b11010 &
b11010 ,
b1001010 *
b11100 )
b11010 "
1!
#53
0!
#54
b10101 %
b11011 '
b1001000 (
b11011 &
b11011 ,
b1001000 *
b11101 )
b11011 "
1!
#55
0!
#56
b10110 %
b11100 '
b1000110 (
b11100 &
b11100 ,
b1000110 *
b11110 )
b11100 "
1!
#57
0!
#58
b10111 %
b11101 '
b1000100 (
b11101 &
b11101 ,
b1000100 *
b11111 )
b11101 "
1!
#59
0!
#60
b11000 %
b11110 '
b1000010 (
b11110 &
b11110 ,
b1000010 *
b100000 )
b11110 "
1!
#61
0!
#62
b11001 %
b11111 '
b1000000 (
b11111 &
b11111 ,
b1000000 *
b100001 )
b11111 "
1!
#63
0!
#64
b11010 %
b0 '
b111111 (
b0 &
b0 ,
b111111 *
b100010 )
b100000 "
1!
#65
0!
#66
b11011 %
b1 '
b111110 (
b1 &
b1 +
b111110 *
b100011 )
b100001 "
1!
#67
0!
#68
b11100 %
b10 '
b111101 (
b10 &
b10 +
b111101 *
b100100 )
b100010 "
1!
#69
0!
#70
b11101 %
b11 '
b111100 (
b11 &
b11 +
b111100 *
b100101 )
b100011 "
1!
#71
0!
#72
b11110 %
b100 '
b111011 (
b100 &
b100 +
b111011 *
b100110 )
b100100 "
1!
#73
0!
#74
b11111 %
b101 '
b111010 (
b101 &
b101 +
b111010 *
b100111 )
b100101 "
1!
#75
0!
#76
b0 %
b110 '
b111001 (
b110 &
b110 +
b111001 *
b101000 )
b100110 "
1!
#77
0!
#78
b1 %
b111 '
b111000 (
b111 &
b111 +
b111000 *
b101001 )
b100111 "
1!
#79
0!
#80
b10 %
b1000 '
b110111 (
b1000 &
b1000 +
b110111 *
b101010 )
b101000 "
1!
#81
0!
#82
b11 %
b1001 '
b110110 (
b1001 &
b1001 +
b110110 *
b101011 )
b101001 "
1!
#83
0!
#84
b100 %
b1010 '
b110101 (
b1010 &
b1010 +
b110101 *
b101100 )
b101010 "
1!
#85
0!
#86
b101 %
b1011 '
b110100 (
b1011 &
b1011 +
b110100 *
b101101 )
b101011 "
1!
#87
0!
#88
b110 %
b1100 '
b110011 (
b1100 &
b1100 +
b110011 *
b101110 )
b101100 "
1!
#89
0!
#90
b111 %
b1101 '
b110010 (
b1101 &
b1101 +
b110010 *
b101111 )
b101101 "
1!
#91
0!
#92
b1000 %
b1110 '
b110001 (
b1110 &
b1110 +
b110001 *
b110000 )
b101110 "
1!
#93
0!
#94
b1001 %
b1111 '
b110000 (
b1111 &
b1111 +
b110000 *
b110001 )
b101111 "
1!
#95
0!
#96
b1010 %
b10000 '
b101111 (
b10000 &
b10000 +
b101111 *
b110010 )
b110000 "
1!
#97
0!
#98
b1011 %
b10001 '
b101110 (
b10001 &
b10001 +
b101110 *
b110011 )
b110001 "
1!
#99
0!
#100
b1100 %
b10010 '
b101101 (
b10010 &
b10010 +
b101101 *
b110100 )
b110010 "
1!
#101
0!
#102
b1101 %
b10011 '
b101100 (
b10011 &
b10011 +
b101100 *
b110101 )
b110011 "
1!
#103
0!
#104
b1110 %
b10100 '
b101011 (
b10100 &
b10100 +
b101011 *
b110110 )
b110100 "
1!
#105
0!
#106
b1111 %
b10101 '
b101010 (
b10101 &
b10101 +
b101010 *
b110111 )
b110101 "
1!
#107
0!
#108
b10000 %
b10110 '
b101001 (
b10110 &
b10110 +
b101001 *
b111000 )
b110110 "
1!
#109
0!
#110
b10001 %
b10111 '
b101000 (
b10111 &
b10111 +
b101000 *
b111001 )
b110111 "
1!
#111
0!
#112
b10010 %
b11000 '
b100111 (
b11000 &
b11000 +
b100111 *
b111010 )
b111000 "
1!
#113
0!
#114
b10011 %
b11001 '
b100110 (
b11001 &
b11001 +
b100110 *
b111011 )
b111001 "
1!
#115
0!
#116
b10100 %
b11010 '
b100101 (
b11010 &
b11010 +
b100101 *
b111100 )
b111010 "
1!
#117
0!
#118
b10101 %
b11011 '
b100100 (
b11011 &
b11011 +
b100100 *
b111101 )
b111011 "
1!
#119
0!
#120
b10110 %
b11100 '
b100011 (
b11100 &
b11100 +
b100011 *
b111110 )
b111100 "
1!
#121
0!
#122
b10111 %
b11101 '
b100010 (
b11101 &
b11101 +
b100010 *
b111111 )
b111101 "
1!
#123
0!
#124
b11000 %
b11110 '
b100001 (
b11110 &
b11110 +
b100001 *
b1000000 )
b111110 "
1!
#125
0!
#126
b11001 %
b11111 '
b100000 (
b11111 &
b11111 +
b100000 *
b1000001 )
b111111 "
1!
#127
0!
#128
b11010 %
b0 '
b11111 (
b0 &
b0 +
b11111 *
b1000010 )
b1000000 "
1!
#129
0!
#130
b11011 %
b10 '
b11110 (
b10 &
b10 +
b11110 *
b1000011 )
b1000001 "
1!
#131
0!
#132
b11100 %
b1 '
b11111 (
b1 ,
b1 &
b0 +
b11111 *
b1000100 )
b1000010 "
1!
#133
0!
#134
b11101 %
b11 '
b11110 (
b11 &
b10 +
b11110 *
b1000101 )
b1000011 "
1!
#135
0!
#136
b11110 %
b100 '
b11101 (
b0 ,
b100 &
b100 +
b11101 *
b1000110 )
b1000100 "
1!
#137
0!
#138
b11111 %
b110 '
b11100 (
b110 &
b110 +
b11100 *
b1000111 )
b1000101 "
1!
#139
0!
#140
b0 %
b101 '
b11101 (
b1 ,
b101 &
b100 +
b11101 *
b1001000 )
b1000110 "
1!
#141
0!
#142
b10 %
b111 '
b11100 (
b111 &
b110 +
b11100 *
b1001001 )
b1000111 "
1!
#143
0!
#144
b1 %
b1000 '
b11011 (
b0 ,
b1000 &
b1000 +
b11011 *
b1001010 )
b1001000 "
1!
#145
0!
#146
b11 %
b1010 '
b11010 (
b1010 &
b1010 +
b11010 *
b1001011 )
b1001001 "
1!
#147
0!
#148
b100 %
b1001 '
b11011 (
b1 ,
b1001 &
b1000 +
b11011 *
b1001100 )
b1001010 "
1!
#149
0!
#150
b110 %
b1011 '
b11010 (
b1011 &
b1010 +
b11010 *
b1001101 )
b1001011 "
1!
#151
0!
#152
b101 %
b1100 '
b11001 (
b0 ,
b1100 &
b1100 +
b11001 *
b1001110 )
b1001100 "
1!
#153
0!
#154
b111 %
b1110 '
b11000 (
b1110 &
b1110 +
b11000 *
b1001111 )
b1001101 "
1!
#155
0!
#156
b1000 %
b1101 '
b11001 (
b1 ,
b1101 &
b1100 +
b11001 *
b1010000 )
b1001110 "
1!
#157
0!
#158
b1010 %
b1111 '
b11000 (
b1111 &
b1110 +
b11000 *
b1010001 )
b1001111 "
1!
#159
0!
#160
b1001 %
b10000 '
b10111 (
b0 ,
b10000 &
b10000 +
b10111 *
b1010010 )
b1010000 "
1!
#161
0!
#162
b1011 %
b10010 '
b10110 (
b10010 &
b10010 +
b10110 *
b1010011 )
b1010001 "
1!
#163
0!
#164
b1100 %
b10001 '
b10111 (
b1 ,
b10001 &
b10000 +
b10111 *
b1010100 )
b1010010 "
1!
#165
0!
#166
b1110 %
b10011 '
b10110 (
b10011 &
b10010 +
b10110 *
b1010101 )
b1010011 "
1!
#167
0!
#168
b1101 %
b10100 '
b10101 (
b0 ,
b10100 &
b10100 +
b10101 *
b1010110 )
b1010100 "
1!
#169
0!
#170
b1111 %
b10110 '
b10100 (
b10110 &
b10110 +
b10100 *
b1010111 )
b1010101 "
1!
#171
0!
#172
b10000 %
b10101 '
b10101 (
b1 ,
b10101 &
b10100 +
b10101 *
b1011000 )
b1010110 "
1!
#173
0!
#174
b10010 %
b10111 '
b10100 (
b10111 &
b10110 +
b10100 *
b1011001 )
b1010111 "
1!
#175
0!
#176
b10001 %
b11000 '
b10011 (
b0 ,
b11000 &
b11000 +
b10011 *
b1011010 )
b1011000 "
1!
#177
0!
#178
b10011 %
b11010 '
b10010 (
b11010 &
b11010 +
b10010 *
b1011011 )
b1011001 "
1!
#179
0!
#180
b10100 %
b11001 '
b10011 (
b1 ,
b11001 &
b11000 +
b10011 *
b1011100 )
b1011010 "
1!
#181
0!
#182
b10110 %
b11011 '
b10010 (
b11011 &
b11010 +
b10010 *
b1011101 )
b1011011 "
1!
#183
0!
#184
b10101 %
b11100 '
b10001 (
b0 ,
b11100 &
b11100 +
b10001 *
b1011110 )
b1011100 "
1!
#185
0!
#186
b10111 %
b11110 '
b10000 (
b11110 &
b11110 +
b10000 *
b1011111 )
b1011101 "
1!
#187
0!
#188
b11000 %
b11101 '
b10001 (
b1 ,
b11101 &
b11100 +
b10001 *
b1100000 )
b1011110 "
1!
#189
0!
#190
b11010 %
b11111 '
b10000 (
b11111 &
b11110 +
b10000 *
b1100001 )
b1011111 "
1!
#191
0!
#192
b11001 %
b0 '
b1111 (
b0 ,
b0 &
b0 +
b1111 *
b1100010 )
b1100000 "
1!
#193
0!
#194
b11011 %
b100 '
b1110 (
b100 &
b100 +
b1110 *
b1100011 )
b1100001 "
1!
#195
0!
#196
b11100 %
b1 '
b1111 (
b1 ,
b1 &
b0 +
b1111 *
b1100100 )
b1100010 "
1!
#197
0!
#198
b11110 %
b101 '
b1110 (
b101 &
b100 +
b1110 *
b1100101 )
b1100011 "
1!
#199
0!
#200
b11101 %
b10 '
b1111 (
b10 ,
b10 &
b0 +
b1111 *
b1100110 )
b1100100 "
1!
#201
0!
#202
b11111 %
b110 '
b1110 (
b110 &
b100 +
b1110 *
b1100111 )
b1100101 "
1!
#203
0!
#204
b0 %
b11 '
b1111 (
b11 ,
b11 &
b0 +
b1111 *
b1101000 )
b1100110 "
1!
#205
0!
#206
b100 %
b111 '
b1110 (
b111 &
b100 +
b1110 *
b1101001 )
b1100111 "
1!
#207
0!
#208
b1 %
b1000 '
b1101 (
b0 ,
b1000 &
b1000 +
b1101 *
b1101010 )
b1101000 "
1!
#209
0!
#210
b101 %
b1100 '
b1100 (
b1100 &
b1100 +
b1100 *
b1101011 )
b1101001 "
1!
#211
0!
#212
b10 %
b1001 '
b1101 (
b1 ,
b1001 &
b1000 +
b1101 *
b1101100 )
b1101010 "
1!
#213
0!
#214
b110 %
b1101 '
b1100 (
b1101 &
b1100 +
b1100 *
b1101101 )
b1101011 "
1!
#215
0!
#216
b11 %
b1010 '
b1101 (
b10 ,
b1010 &
b1000 +
b1101 *
b1101110 )
b1101100 "
1!
#217
0!
#218
b111 %
b1110 '
b1100 (
b1110 &
b1100 +
b1100 *
b1101111 )
b1101101 "
1!
#219
0!
#220
b1000 %
b1011 '
b1101 (
b11 ,
b1011 &
b1000 +
b1101 *
b1110000 )
b1101110 "
1!
#221
0!
#222
b1100 %
b1111 '
b1100 (
b1111 &
b1100 +
b1100 *
b1110001 )
b1101111 "
1!
#223
0!
#224
b1001 %
b10000 '
b1011 (
b0 ,
b10000 &
b10000 +
b1011 *
b1110010 )
b1110000 "
1!
#225
0!
#226
b1101 %
b10100 '
b1010 (
b10100 &
b10100 +
b1010 *
b1110011 )
b1110001 "
1!
#227
0!
#228
b1010 %
b10001 '
b1011 (
b1 ,
b10001 &
b10000 +
b1011 *
b1110100 )
b1110010 "
1!
#229
0!
#230
b1110 %
b10101 '
b1010 (
b10101 &
b10100 +
b1010 *
b1110101 )
b1110011 "
1!
#231
0!
#232
b1011 %
b10010 '
b1011 (
b10 ,
b10010 &
b10000 +
b1011 *
b1110110 )
b1110100 "
1!
#233
0!
#234
b1111 %
b10110 '
b1010 (
b10110 &
b10100 +
b1010 *
b1110111 )
b1110101 "
1!
#235
0!
#236
b10000 %
b10011 '
b1011 (
b11 ,
b10011 &
b10000 +
b1011 *
b1111000 )
b1110110 "
1!
#237
0!
#238
b10100 %
b10111 '
b1010 (
b10111 &
b10100 +
b1010 *
b1111001 )
b1110111 "
1!
#239
0!
#240
b10001 %
b11000 '
b1001 (
b0 ,
b11000 &
b11000 +
b1001 *
b1111010 )
b1111000 "
1!
#241
0!
#242
b10101 %
b11100 '
b1000 (
b11100 &
b11100 +
b1000 *
b1111011 )
b1111001 "
1!
#243
0!
#244
b10010 %
b11001 '
b1001 (
b1 ,
b11001 &
b11000 +
b1001 *
b1111100 )
b1111010 "
1!
#245
0!
#246
b10110 %
b11101 '
b1000 (
b11101 &
b11100 +
b1000 *
b1111101 )
b1111011 "
1!
#247
0!
#248
b10011 %
b11010 '
b1001 (
b10 ,
b11010 &
b11000 +
b1001 *
b1111110 )
b1111100 "
1!
#249
0!
#250
b10111 %
b11110 '
b1000 (
b11110 &
b11100 +
b1000 *
b1111111 )
b1111101 "
1!
#251
0!
#252
b11000 %
b11011 '
b1001 (
b11 ,
b11011 &
b11000 +
b1001 *
b10000000 )
b1111110 "
1!
#253
0!
#254
b11100 %
b11111 '
b1000 (
b11111 &
b11100 +
b1000 *
b10000001 )
b1111111 "
1!
#255
0!
#256
b11001 %
b0 '
b111 (
b0 ,
b0 &
b0 +
b111 *
b10000010 )
b10000000 "
1!
#257
0!
#258
b11101 %
b1000 '
b110 (
b1000 &
b1000 +
b110 *
b10000011 )
b10000001 "
1!
#259
0!
#260
b11010 %
b1 '
b111 (
b1 ,
b1 &
b0 +
b111 *
b10000100 )
b10000010 "
1!
#261
0!
#262
b11110 %
b1001 '
b110 (
b1001 &
b1000 +
b110 *
b10000101 )
b10000011 "
1!
#263
0!
#264
b11011 %
b10 '
b111 (
b10 ,
b10 &
b0 +
b111 *
b10000110 )
b10000100 "
1!
#265
0!
#266
b11111 %
b1010 '
b110 (
b1010 &
b1000 +
b110 *
b10000111 )
b10000101 "
1!
#267
0!
#268
b0 %
b11 '
b111 (
b11 ,
b11 &
b0 +
b111 *
b10001000 )
b10000110 "
1!
#269
0!
#270
b1000 %
b1011 '
b110 (
b1011 &
b1000 +
b110 *
b10001001 )
b10000111 "
1!
#271
0!
#272
b1 %
b100 '
b111 (
b100 ,
b100 &
b0 +
b111 *
b10001010 )
b10001000 "
1!
#273
0!
#274
b1001 %
b1100 '
b110 (
b1100 &
b1000 +
b110 *
b10001011 )
b10001001 "
1!
#275
0!
#276
b10 %
b101 '
b111 (
b101 ,
b101 &
b0 +
b111 *
b10001100 )
b10001010 "
1!
#277
0!
#278
b1010 %
b1101 '
b110 (
b1101 &
b1000 +
b110 *
b10001101 )
b10001011 "
1!
#279
0!
#280
b11 %
b110 '
b111 (
b110 ,
b110 &
b0 +
b111 *
b10001110 )
b10001100 "
1!
#281
0!
#282
b1011 %
b1110 '
b110 (
b1110 &
b1000 +
b110 *
b10001111 )
b10001101 "
1!
#283
0!
#284
b100 %
b111 '
b111 (
b111 ,
b111 &
b0 +
b111 *
b10010000 )
b10001110 "
1!
#285
0!
#286
b1100 %
b1111 '
b110 (
b1111 &
b1000 +
b110 *
b10010001 )
b10001111 "
1!
#287
0!
#288
b101 %
b10000 '
b101 (
b0 ,
b10000 &
b10000 +
b101 *
b10010010 )
b10010000 "
1!
#289
0!
#290
b1101 %
b11000 '
b100 (
b11000 &
b11000 +
b100 *
b10010011 )
b10010001 "
1!
#291
0!
#292
b110 %
b10001 '
b101 (
b1 ,
b10001 &
b10000 +
b101 *
b10010100 )
b10010010 "
1!
#293
0!
#294
b1110 %
b11001 '
b100 (
b11001 &
b11000 +
b100 *
b10010101 )
b10010011 "
1!
#295
0!
#296
b111 %
b10010 '
b101 (
b10 ,
b10010 &
b10000 +
b101 *
b10010110 )
b10010100 "
1!
#297
0!
#298
b1111 %
b11010 '
b100 (
b11010 &
b11000 +
b100 *
b10010111 )
b10010101 "
1!
#299
0!
#300
b10000 %
b10011 '
b101 (
b11 ,
b10011 &
b10000 +
b101 *
b10011000 )
b10010110 "
1!
#301
0!
#302
b11000 %
b11011 '
b100 (
b11011 &
b11000 +
b100 *
b10011001 )
b10010111 "
1!
#303
0!
#304
b10001 %
b10100 '
b101 (
b100 ,
b10100 &
b10000 +
b101 *
b10011010 )
b10011000 "
1!
#305
0!
#306
b11001 %
b11100 '
b100 (
b11100 &
b11000 +
b100 *
b10011011 )
b10011001 "
1!
#307
0!
#308
b10010 %
b10101 '
b101 (
b101 ,
b10101 &
b10000 +
b101 *
b10011100 )
b10011010 "
1!
#309
0!
#310
b11010 %
b11101 '
b100 (
b11101 &
b11000 +
b100 *
b10011101 )
b10011011 "
1!
#311
0!
#312
b10011 %
b10110 '
b101 (
b110 ,
b10110 &
b10000 +
b101 *
b10011110 )
b10011100 "
1!
#313
0!
#314
b11011 %
b11110 '
b100 (
b11110 &
b11000 +
b100 *
b10011111 )
b10011101 "
1!
#315
0!
#316
b10100 %
b10111 '
b101 (
b111 ,
b10111 &
b10000 +
b101 *
b10100000 )
b10011110 "
1!
#317
0!
#318
b11100 %
b11111 '
b100 (
b11111 &
b11000 +
b100 *
b10100001 )
b10011111 "
1!
#319
0!
#320
b10101 %
b0 '
b11 (
b0 ,
b0 &
b0 +
b11 *
b10100010 )
b10100000 "
1!
#321
0!
#322
b11101 %
b10000 '
b10 (
b10000 &
b10000 +
b10 *
b10100011 )
b10100001 "
1!
#323
0!
#324
b10110 %
b1 '
b11 (
b1 ,
b1 &
b0 +
b11 *
b10100100 )
b10100010 "
1!
#325
0!
#326
b11110 %
b10001 '
b10 (
b10001 &
b10000 +
b10 *
b10100101 )
b10100011 "
1!
#327
0!
#328
b10111 %
b10 '
b11 (
b10 ,
b10 &
b0 +
b11 *
b10100110 )
b10100100 "
1!
#329
0!
#330
b11111 %
b10010 '
b10 (
b10010 &
b10000 +
b10 *
b10100111 )
b10100101 "
1!
#331
0!
#332
b0 %
b11 '
b11 (
b11 ,
b11 &
b0 +
b11 *
b10101000 )
b10100110 "
1!
#333
0!
#334
b10000 %
b10011 '
b10 (
b10011 &
b10000 +
b10 *
b10101001 )
b10100111 "
1!
#335
0!
#336
b1 %
b100 '
b11 (
b100 ,
b100 &
b0 +
b11 *
b10101010 )
b10101000 "
1!
#337
0!
#338
b10001 %
b10100 '
b10 (
b10100 &
b10000 +
b10 *
b10101011 )
b10101001 "
1!
#339
0!
#340
b10 %
b101 '
b11 (
b101 ,
b101 &
b0 +
b11 *
b10101100 )
b10101010 "
1!
#341
0!
#342
b10010 %
b10101 '
b10 (
b10101 &
b10000 +
b10 *
b10101101 )
b10101011 "
1!
#343
0!
#344
b11 %
b110 '
b11 (
b110 ,
b110 &
b0 +
b11 *
b10101110 )
b10101100 "
1!
#345
0!
#346
b10011 %
b10110 '
b10 (
b10110 &
b10000 +
b10 *
b10101111 )
b10101101 "
1!
#347
0!
#348
b100 %
b111 '
b11 (
b111 ,
b111 &
b0 +
b11 *
b10110000 )
b10101110 "
1!
#349
0!
#350
b10100 %
b10111 '
b10 (
b10111 &
b10000 +
b10 *
b10110001 )
b10101111 "
1!
#351
0!
#352
b101 %
b1000 '
b11 (
b1000 ,
b1000 &
b0 +
b11 *
b10110010 )
b10110000 "
1!
#353
0!
#354
b10101 %
b11000 '
b10 (
b11000 &
b10000 +
b10 *
b10110011 )
b10110001 "
1!
#355
0!
#356
b110 %
b1001 '
b11 (
b1001 ,
b1001 &
b0 +
b11 *
b10110100 )
b10110010 "
1!
#357
0!
#358
b10110 %
b11001 '
b10 (
b11001 &
b10000 +
b10 *
b10110101 )
b10110011 "
1!
#359
0!
#360
b111 %
b1010 '
b11 (
b1010 ,
b1010 &
b0 +
b11 *
b10110110 )
b10110100 "
1!
#361
0!
#362
b10111 %
b11010 '
b10 (
b11010 &
b10000 +
b10 *
b10110111 )
b10110101 "
1!
#363
0!
#364
b1000 %
b1011 '
b11 (
b1011 ,
b1011 &
b0 +
b11 *
b10111000 )
b10110110 "
1!
#365
0!
#366
b11000 %
b11011 '
b10 (
b11011 &
b10000 +
b10 *
b10111001 )
b10110111 "
1!
#367
0!
#368
b1001 %
b1100 '
b11 (
b1100 ,
b1100 &
b0 +
b11 *
b10111010 )
b10111000 "
1!
#369
0!
#370
b11001 %
b11100 '
b10 (
b11100 &
b10000 +
b10 *
b10111011 )
b10111001 "
1!
#371
0!
#372
b1010 %
b1101 '
b11 (
b1101 ,
b1101 &
b0 +
b11 *
b10111100 )
b10111010 "
1!
#373
0!
#374
b11010 %
b11101 '
b10 (
b11101 &
b10000 +
b10 *
b10111101 )
b10111011 "
1!
#375
0!
#376
b1011 %
b1110 '
b11 (
b1110 ,
b1110 &
b0 +
b11 *
b10111110 )
b10111100 "
1!
#377
0!
#378
b11011 %
b11110 '
b10 (
b11110 &
b10000 +
b10 *
b10111111 )
b10111101 "
1!
#379
0!
#380
b1100 %
b1111 '
b11 (
b1111 ,
b1111 &
b0 +
b11 *
b11000000 )
b10111110 "
1!
#381
0!
#382
b11100 %
b11111 '
b10 (
b11111 &
b10000 +
b10 *
b11000001 )
b10111111 "
1!
#383
0!
#384
b1101 %
b0 '
b1 (
b0 ,
b0 &
b0 +
b1 *
b11000010 )
b11000000 "
1!
#385
0!
#386
b11101 %
b1 '
b1 &
b1 ,
b11000011 )
b11000001 "
1!
#387
0!
#388
b1110 %
b10 '
b10 &
b10 ,
b11000100 )
b11000010 "
1!
#389
0!
#390
b11110 %
b11 '
b11 &
b11 ,
b11000101 )
b11000011 "
1!
#391
0!
#392
b1111 %
b100 '
b100 &
b100 ,
b11000110 )
b11000100 "
1!
#393
0!
#394
b11111 %
b101 '
b101 &
b101 ,
b11000111 )
b11000101 "
1!
#395
0!
#396
b0 %
b110 '
b110 &
b110 ,
b11001000 )
b11000110 "
1!
#397
0!
#398
b1 %
b111 '
b111 &
b111 ,
b11001001 )
b11000111 "
1!
#399
0!
#400
b10 %
b1000 '
b1000 &
b1000 ,
b11001010 )
b11001000 "
1!
#401
0!
#402
b11 %
b1001 '
b1001 &
b1001 ,
b11001011 )
b11001001 "
1!
#403
0!
#404
b100 %
b1010 '
b1010 &
b1010 ,
b11001100 )
b11001010 "
1!
#405
0!
#406
b101 %
b1011 '
b1011 &
b1011 ,
b11001101 )
b11001011 "
1!
