src/sub.v
module sub(
    output[11:0] res,
    input[11:0] in1,
    input[11:0] in2,
    input[1:0] mode
);
wire [12:0] diff;
wire [11:0] reduce_diff;
assign diff = in1 - in2;
assign reduce_diff = diff[12] == 1 ? diff + 12'd3329 : diff;
assign res = mode == 2'd1 ?  (reduce_diff[0] ? reduce_diff[11:1] + 12'd1665 : reduce_diff[11:1]): reduce_diff;
endmodule

src/NTT/add.v
module add(
    input[11:0] in1,
    input[11:0] in2,
    input[1:0] mode,
    output[11:0] res
);
wire [12:0] sum;
wire [11:0] reduce_sum;
assign sum = in1 + in2;
assign reduce_sum = sum >= 3329 ? sum - 12'd3329 : sum;
assign res = mode == 2'd1 ? (reduce_sum[0] ? reduce_sum[11:1] + 12'd1665 : reduce_sum[11:1]): reduce_sum;
endmodule

layout/reduce.v
module reduce (
    input clk,
    input rst,
    input [23:0] c,
    output [11:0] r
);

// segment 1
// Calculate Q'1 (Q_1) with low-complexity division by 13.
wire [7:0] c0;
wire [15:0] c1;
wire [13:0] d_1;
wire [13:0] d1_sum;
wire [12:0] Q_1;
assign c0 = c[7:0];
assign c1 = c[23:8];
assign d_1 = c1[15:3] + c1[15:5]; 
assign d1_sum = d_1 - d_1[13:6];
assign Q_1 = d1_sum[13:1];

// stage 1 registers
reg [7:0] c0_reg;
reg [5:0] c1_reg;
reg [12:0] Q_1_reg;
always @(posedge clk or posedge rst) begin
    if(rst) begin
        Q_1_reg <= 0;
        c1_reg <= 0;
        c0_reg <= 0;
    end
    else begin
        Q_1_reg <= Q_1;
        c1_reg <= c1[5:0];
        c0_reg <= c0;
    end
end

// segment 2
// Calculate r'1 (r_1) ~= c1 mod13 with a short width addition tree.
wire [5:0] s_1;
wire [5:0] s_2;
wire [5:0] r_1;
wire [13:0] r1c0;
assign s_1[5:3] = c1_reg[5:3] - Q_1_reg[2:0];
assign s_1[2:0] = c1_reg[2:0];
assign s_2[5:2] = Q_1_reg[5:2] + Q_1_reg[3:0];
assign s_2[1:0] = Q_1_reg[1:0];
assign r_1 = s_1 - s_2;
assign r1c0 = {r_1, c0_reg};

// segment 3
// Obtain raw remander R and calculate r = R mod 3329.
wire [13:0] R;
reg [13:0] R_reg;
assign R = r1c0 - Q_1_reg;
always @(posedge clk or posedge rst) begin
    if(rst) R_reg = 0;
    else R_reg <= R;
end
assign r = R_reg[13] | (R_reg[12:0] >= 13'd3329) ? 
                       (R_reg[11:0] + (R_reg[13] ? 12'd3329 : -12'd3329))
                     : R_reg[11:0];

    
endmodule

src/NTT/mult.v
`include "reduce.v"

module mult(
    output [11:0] res,
    input [11:0] in1,
    input [11:0]in2,
    input clk,
    input rst
);
    reg [11:0] reg1;
    reg [11:0] reg2;
    always @(posedge clk or posedge rst)
    begin
        if(rst)
        begin
            reg1 <= 0;
            reg2 <= 0;
        end
        else
        begin
            reg1 <= in1;
            reg2 <= in2;
        end
    end
    wire [23:0]product;
    assign product = reg1*reg2;
    reg [23:0] product_reg;
    always @(posedge clk)begin
        product_reg <= product;
    end
    reduce mod(clk, rst, product_reg, res);
endmodule

src/NTT/butterfly_core.v
`timescale 1ns / 1ps
// `include "add.v"
// `include "sub.v"
// `include "mult.v"

module butterfly_core(
    input clk,
    input rst,
    input [11:0] in_1,
    input [11:0] in_2,
    input [11:0] coef,
    input [1:0] mode,
    output [11:0] out_1,
    output [11:0] out_2
    );

/*
mode 0: NTT & mul_stage_2 (mul reduce -> add sub, total 5 delay)
mode 1: INVNTT (add sub -> mul reduce, total 5 delay)
mode 2: Point Wise Multiply (4 delay)
*/
`define NTT 2'd0
`define INTT 2'd1
`define MULT 2'd2
`define ADDSUB 2'd3

// mult & reduce
wire [11:0] mult_in_1;
wire [11:0] mult_in_2;
wire [11:0] mult_coef_in;
wire [11:0] mult_out_1;
wire [11:0] mult_out_2;
reg [11:0] mult_in_1_reg [0:3]; // use for timing output (delay 4 circles)
integer i;
mult multiply (
    .clk(clk),
    .rst(rst),
    .in1(mult_in_2),
    .in2(mult_coef_in),
    .res(mult_out_2)
);
always @(posedge clk or posedge rst) begin
    if (rst)begin
        for(i = 0; i < 4; i = i+1)begin
            mult_in_1_reg[i] <= 0;
        end
    end
    else begin
        mult_in_1_reg[0] <= mult_in_1;
        for(i = 1; i < 4; i = i+1)begin
            mult_in_1_reg[i] <= mult_in_1_reg[i-1];
        end
    end

end
assign mult_out_1 = mult_in_1_reg[3];

// add & sub
wire [11:0] addsub_in_1;
wire [11:0] addsub_in_2;
wire [11:0] addsub_out_1;
wire [11:0] addsub_out_2;
reg [11:0]  addsub_in_1_reg;
reg [11:0]  addsub_in_2_reg;
add addition (
    .mode(mode),
    .in1(addsub_in_1_reg),
    .in2(addsub_in_2_reg),
    .res(addsub_out_1)
);
sub subtraction (
    .mode(mode),
    .in1(addsub_in_1_reg),
    .in2(addsub_in_2_reg),
    .res(addsub_out_2)
);

always @(posedge clk or posedge rst) begin
    if(rst) begin
        addsub_in_1_reg <= 0;
        addsub_in_2_reg <= 0;
    end
    else begin
        addsub_in_1_reg <= addsub_in_1;
        addsub_in_2_reg <= addsub_in_2;
    end
end

// input select multiplexers
reg [11:0] mult_coef_in_reg;
always @(posedge clk or posedge rst) begin
    if(rst) mult_coef_in_reg <= 0;
    else mult_coef_in_reg <= coef;
end
assign mult_in_1 = mode == `INTT || mode == `ADDSUB? addsub_out_1 : in_1;
assign mult_in_2 = mode == `INTT || mode == `ADDSUB? addsub_out_2 : in_2;
assign mult_coef_in = mode == `INTT || mode == `ADDSUB? mult_coef_in_reg : coef;
assign addsub_in_1 = mode == `INTT || mode == `ADDSUB? in_1 : mult_out_1;
assign addsub_in_2 = mode == `INTT || mode == `ADDSUB? in_2 : mult_out_2;

// output select multiplexers
assign out_1 = mode == `NTT || mode == `ADDSUB? addsub_out_1 : mult_out_1;
assign out_2 = mode == `NTT || mode == `ADDSUB? addsub_out_2 : mult_out_2;

endmodule

src/NTT/buterfly_tb.v
`timescale 1us/1us
`include "butterfly_core.v"

module bu_tb;
reg clk;
reg rst;
reg [1:0] mode; // 0:NTT, 1:INVNTT, 2:MULT, 3:ADDSUB
reg [11:0] in_1;
reg [11:0] in_2;
reg [11:0] coef;
wire [11:0] out_1;
wire [11:0] out_2;
butterfly_core BU(
    .clk(clk),
    .rst(rst),
    .in_1(in_1),
    .in_2(in_2),
    .coef(coef),
    .mode(mode),
    .out_1(out_1),
    .out_2(out_2)
    );
initial begin
    $dumpfile("bu_tb.vcd");
    $dumpvars(0, BU);
    #0
    rst = 1;
    mode = 0; // 0:NTT, 1:INVNTT, 2:MULT, 3:ADDSUB
    #10
    rst = 0;
    mode = 0;
    in_1 = 12'd123;
    in_2 = 12'd345;
    coef = 12'd50;
    #2
    in_1 = 12'd0;
    in_2 = 12'd345;
    coef = 12'd50;
    #2
    in_1 = 12'd50;
    in_2 = 12'd3328;
    coef = 12'd2;
    #30
    rst = 1;
    mode = 1; // 0:NTT, 1:INVNTT, 2:MULT, 3:ADDSUB
    #2
    rst = 0;
    mode = 1;
    in_2 = 12'd728;
    in_1 = 12'd2847;
    coef = 12'd3279;
    #2
    in_2 = 12'd605;
    in_1 = 12'd2724;
    coef = 12'd3279;
    #2
    in_2 = 12'd48;
    in_1 = 12'd52;
    coef = 12'd3327;
    #30
    rst = 1;
    mode = 2; // 0:NTT, 1:INVNTT, 2:MULT, 3:ADDSUB
    #2
    rst = 0;
    mode = 2;
    in_2 = 12'd728;
    in_1 = 12'd2847;
    coef = 12'd3279;
    #2
    in_2 = 12'd605;
    in_1 = 12'd2724;
    coef = 12'd3279;
    #2
    in_2 = 12'd48;
    in_1 = 12'd52;
    coef = 12'd3327;
    #20 
    rst = 1;
    mode = 3; // 0:NTT, 1:INVNTT, 2:MULT, 3:ADDSUB
    #2
    rst = 0;
    mode = 3;
    in_2 = 12'd728;
    in_1 = 12'd2847;
    coef = 12'd3279;
    #2
    in_2 = 12'd605;
    in_1 = 12'd2724;
    coef = 12'd3279;
    #2
    in_2 = 12'd48;
    in_1 = 12'd52;
    coef = 12'd3327;
    #20
    $finish;
end
initial begin
    clk = 1;
    forever begin
        #1 clk = ~clk;
    end
end
endmodule

src/NTT/bu_tb.vcd
$date
	Sun Feb 16 17:23:30 2025
$end
$version
	Icarus Verilog
$end
$timescale
	1ps
$end
$scope module bu_tb $end
$scope module BU $end
$var wire 1 ! clk $end
$var wire 12 " coef [11:0] $end
$var wire 12 # in_1 [11:0] $end
$var wire 12 $ in_2 [11:0] $end
$var wire 2 % mode [1:0] $end
$var wire 12 & mult_out_1 [11:0] $end
$var wire 1 ' rst $end
$var wire 12 ( out_2 [11:0] $end
$var wire 12 ) out_1 [11:0] $end
$var wire 12 * mult_out_2 [11:0] $end
$var wire 12 + mult_in_2 [11:0] $end
$var wire 12 , mult_in_1 [11:0] $end
$var wire 12 - mult_coef_in [11:0] $end
$var wire 12 . addsub_out_2 [11:0] $end
$var wire 12 / addsub_out_1 [11:0] $end
$var wire 12 0 addsub_in_2 [11:0] $end
$var wire 12 1 addsub_in_1 [11:0] $end
$var reg 12 2 addsub_in_1_reg [11:0] $end
$var reg 12 3 addsub_in_2_reg [11:0] $end
$var reg 12 4 mult_coef_in_reg [11:0] $end
$var integer 32 5 i [31:0] $end
$scope module addition $end
$var wire 12 6 in1 [11:0] $end
$var wire 12 7 in2 [11:0] $end
$var wire 2 8 mode [1:0] $end
$var wire 13 9 sum [12:0] $end
$var wire 12 : res [11:0] $end
$var wire 12 ; reduce_sum [11:0] $end
$upscope $end
$scope module multiply $end
$var wire 1 ! clk $end
$var wire 12 < in1 [11:0] $end
$var wire 12 = in2 [11:0] $end
$var wire 1 ' rst $end
$var wire 12 > res [11:0] $end
$var wire 24 ? product [23:0] $end
$var reg 24 @ product_reg [23:0] $end
$var reg 12 A reg1 [11:0] $end
$var reg 12 B reg2 [11:0] $end
$scope module mod $end
$var wire 24 C c [23:0] $end
$var wire 1 ! clk $end
$var wire 1 ' rst $end
$var wire 6 D s_2 [5:0] $end
$var wire 6 E s_1 [5:0] $end
$var wire 6 F r_1 [5:0] $end
$var wire 14 G r1c0 [13:0] $end
$var wire 12 H r [11:0] $end
$var wire 14 I d_1 [13:0] $end
$var wire 14 J d1_sum [13:0] $end
$var wire 16 K c1 [15:0] $end
$var wire 8 L c0 [7:0] $end
$var wire 14 M R [13:0] $end
$var wire 13 N Q_1 [12:0] $end
$var reg 13 O Q_1_reg [12:0] $end
$var reg 14 P R_reg [13:0] $end
$var reg 8 Q c0_reg [7:0] $end
$var reg 6 R c1_reg [5:0] $end
$upscope $end
$upscope $end
$scope module subtraction $end
$var wire 12 S in1 [11:0] $end
$var wire 12 T in2 [11:0] $end
$var wire 2 U mode [1:0] $end
$var wire 12 V res [11:0] $end
$var wire 12 W reduce_diff [11:0] $end
$var wire 13 X diff [12:0] $end
$upscope $end
$upscope $end
$upscope $end
$enddefinitions $end
$comment Show the parameter values. $end
$dumpall
$end
#0
$dumpvars
b0 X
b0 W
b0 V
b0 U
b0 T
b0 S
b0 R
b0 Q
bx P
b0 O
bx N
b0 M
bx L
bx K
bx J
bx I
bx H
b0 G
b0 F
b0 E
b0 D
bx C
b0 B
b0 A
bx @
b0 ?
bx >
bx =
bx <
b0 ;
b0 :
b0 9
b0 8
b0 7
b0 6
b100 5
b0 4
b0 3
b0 2
b0 1
bx 0
b0 /
b0 .
bx -
bx ,
bx +
bx *
b0 )
b0 (
1'
b0 &
b0 %
bx $
bx #
bx "
1!
$end
#1000
0!
#2000
b0 N
b0 J
b0 I
b0 L
b0 K
b0 @
b0 C
b0 0
b0 *
b0 >
b0 H
b0 P
b100 5
1!
#3000
0!
#4000
b100 5
1!
#5000
0!
#6000
b100 5
1!
#7000
0!
#8000
b100 5
1!
#9000
0!
#10000
b100001101100010 ?
b110010 B
b101011001 A
b110010 4
b100 5
b110010 -
b110010 =
b101011001 +
b101011001 <
b1111011 ,
1!
b110010 "
b101011001 $
b1111011 #
0'
#11000
0!
#12000
b101 N
b1010 J
b1010 I
b1100010 L
b1000011 K
b100001101100010 @
b100001101100010 C
b100 5
b0 ,
1!
b0 #
#13000
0!
#14000
b11011 E
b10 F
b11001 D
b1001100010 G
b1100010 Q
b11 R
b1001011101 M
b101 O
b10 B
b1101000000000 ?
b110100000000 A
b10 4
b100 5
b10 -
b10 =
b110100000000 +
b110100000000 <
b110010 ,
1!
b10 "
b110100000000 $
b110010 #
#15000
0!
#16000
b1001011101 0
b1 N
b1001011101 *
b1001011101 >
b1001011101 H
b11 J
b11 I
b1111011 1
b0 L
b11010 K
b1111011 &
b1001011101 P
b1101000000000 @
b1101000000000 C
b100 5
1!
#17000
0!
#18000
b1011011000 )
b101100011111 (
b1011011000 /
b1011011000 :
b101100011111 .
b101100011111 V
b1011011000 ;
b101100011111 W
b10010 E
b1101 F
b101 D
b0 1
b110100000000 G
b0 Q
b11010 R
b110011111111 M
b1 O
b0 &
b1001011101 3
b1001011101 7
b1001011101 T
b1011011000 9
b1111000011110 X
b1111011 2
b1111011 6
b1111011 S
b100 5
1!
#19000
0!
#20000
b1001011101 )
b101010100100 (
b1001011101 /
b1001011101 :
b101010100100 .
b101010100100 V
b110011111111 0
b1001011101 ;
b101010100100 W
b110011111111 *
b110011111111 >
b110011111111 H
b110010 1
b1001011101 9
b1110110100011 X
b0 2
b0 6
b0 S
b110010 &
b110011111111 P
b100 5
1!
#21000
0!
#22000
b110000 )
b110100 (
b110000 /
b110000 :
b110100 .
b110100 V
b110000 ;
b110100 W
b110011111111 3
b110011111111 7
b110011111111 T
b110100110001 9
b1001100110011 X
b110010 2
b110010 6
b110010 S
b100 5
1!
#23000
0!
#24000
b100 5
1!
#25000
0!
#26000
b100 5
1!
#27000
0!
#28000
b100 5
1!
#29000
0!
#30000
b100 5
1!
#31000
0!
#32000
b100 5
1!
#33000
0!
#34000
b100 5
1!
#35000
0!
#36000
b100 5
1!
#37000
0!
#38000
b100 5
1!
#39000
0!
#40000
b100 5
1!
#41000
0!
#42000
b100 5
1!
#43000
0!
#44000
b0 ;
b0 W
b0 -
b0 =
b0 E
b0 G
b0 F
b0 D
b0 4
b0 3
b0 7
b0 T
b0 9
b0 X
b0 2
b0 6
b0 S
b0 &
b0 B
b0 ?
b0 A
b0 R
b0 M
b0 O
b0 *
b0 >
b0 H
b0 ,
b0 +
b0 <
b110100000000 0
b0 )
b0 (
b0 /
b0 :
b0 .
b0 V
b100 5
b0 P
1!
b1 %
b1 8
b1 U
1'
#45000
0!
#46000
b1111011 ,
b101010100100 +
b101010100100 <
b1111011 /
b1111011 :
b101010100100 .
b101010100100 V
b0 N
b11110110 ;
b100001000111 W
b0 J
b0 I
b10010 E
b110100000000 G
b1101 F
b101 D
b110011001111 -
b110011001111 =
b0 K
b11010 R
b110011111111 M
b1 O
b1011011000 3
b1011011000 7
b1011011000 T
b110111110111 9
b100001000111 X
b101100011111 2
b101100011111 6
b101100011111 S
b110011001111 4
b0 @
b0 C
b100 5
b101100011111 1
b1011011000 0
1!
b110011001111 "
b101100011111 #
b1011011000 $
0'
#47000
0!
#48000
b0 ,
b0 /
b0 :
b110011111111 (
b0 ;
b110011111111 *
b110011111111 >
b110011111111 H
b0 E
b0 G
b0 F
b0 D
b1001011101 3
b1001011101 7
b1001011101 T
b110100000001 9
b100001000111 X
b101010100100 2
b101010100100 6
b101010100100 S
b100010000100101010011100 ?
b110011001111 B
b101010100100 A
b110011111111 P
b0 R
b0 M
b0 O
b100 5
b101010100100 1
b1001011101 0
1!
b101010100100 #
b1001011101 $
#49000
0!
#50000
b110010 ,
b10 +
b10 <
b110010 /
b110010 :
b10 .
b10 V
b0 (
b101001111011 N
b0 *
b0 >
b0 H
b1100100 ;
b100 W
b1010011110110 J
b1010101001011 I
b110011111111 -
b110011111111 =
b10011100 L
b1000100001001010 K
b0 P
b110000 3
b110000 7
b110000 T
b1100100 9
b100 X
b110100 2
b110100 6
b110100 S
b110011111111 4
b100010000100101010011100 @
b100010000100101010011100 C
b100 5
b110100 1
b110000 0
1!
b110011111111 "
b110100 #
b110000 $
#51000
0!
#52000
b110010 E
b1011 F
b100111 D
b110011111111 B
b1100111111110 ?
b10 A
b101110011100 G
b10011100 Q
b1010 R
b100100001 M
b101001111011 O
b100 5
1!
#53000
0!
#54000
b100100001 (
b1 N
b100100001 *
b100100001 >
b100100001 H
b11 J
b11 I
b1111011 )
b11111110 L
b11001 K
b100100001 P
b1111011 &
b1100111111110 @
b1100111111110 C
b100 5
1!
#55000
0!
#56000
b0 )
b10001 E
b1100 F
b101 D
b0 &
b110011111110 G
b11111110 Q
b11001 R
b110011111101 M
b1 O
b100 5
1!
#57000
0!
#58000
b110011111101 (
b110011111101 *
b110011111101 >
b110011111101 H
b110010 )
b110011111101 P
b110010 &
b100 5
1!
#59000
0!
#60000
b100 5
1!
#61000
0!
#62000
b100 5
1!
#63000
0!
#64000
b100 5
1!
#65000
0!
#66000
b100 5
1!
#67000
0!
#68000
b100 5
1!
#69000
0!
#70000
b100 5
1!
#71000
0!
#72000
b100 5
1!
#73000
0!
#74000
b100 5
1!
#75000
0!
#76000
b100 5
1!
#77000
0!
#78000
b100 5
1!
#79000
0!
#80000
b0 ;
b0 W
b0 )
b0 E
b0 F
b0 D
b0 4
b0 3
b0 7
b0 T
b0 9
b0 X
b0 2
b0 6
b0 S
b0 &
b0 B
b0 ?
b0 A
b0 G
b0 Q
b0 R
b0 M
b0 O
b0 (
b0 *
b0 >
b0 H
b0 1
b0 0
b110100 ,
b110000 +
b110000 <
b0 /
b0 :
b0 .
b0 V
b100 5
b0 P
1!
b10 %
b10 8
b10 U
1'
#81000
0!
#82000
b0 N
b0 J
b0 I
b10001 E
b1100 F
b101 D
b0 L
b0 K
b110011111110 G
b11111110 Q
b11001 R
b110011111101 M
b1 O
b1001000110110010101000 ?
b110011001111 B
b1011011000 A
b110011001111 4
b0 @
b0 C
b100 5
b110011001111 -
b110011001111 =
b101100011111 ,
b1011011000 +
b1011011000 <
1!
b110011001111 "
b101100011111 #
b1011011000 $
0'
#83000
0!
#84000
b110011111101 (
b110011111101 0
b1011001101 N
b110011111101 *
b110011111101 >
b110011111101 H
b10110011010 J
b10110110000 I
b0 E
b0 F
b0 D
b10101000 L
b10010001101100 K
b111100100010100110011 ?
b1001011101 A
b110011111101 P
b0 G
b0 Q
b0 R
b0 M
b0 O
b1001000110110010101000 @
b1001000110110010101000 C
b100 5
b101010100100 ,
b1001011101 +
b1001011101 <
1!
b101010100100 #
b1001011101 $
#85000
0!
#86000
b0 (
b0 0
b110011111101 /
b110011111101 :
b100 .
b100 V
b1001010100 N
b0 *
b0 >
b0 H
b110011111101 ;
b100 W
b10010101000 J
b10010111010 I
b100 E
b11 F
b1 D
b110011 L
b1111001000101 K
b1110101000 G
b10101000 Q
b101100 R
b11011011 M
b1011001101 O
b0 P
b110011111111 B
b100110111111010000 ?
b110000 A
b110011111101 9
b1001100000011 X
b110011111101 3
b110011111101 7
b110011111101 T
b110011111111 4
b111100100010100110011 @
b111100100010100110011 C
b100 5
b110011111111 -
b110011111111 =
b110100 ,
b110000 +
b110000 <
1!
b110011111111 "
b110100 #
b110000 $
#87000
0!
#88000
b0 /
b0 :
b0 .
b0 V
b11011011 (
b11011011 0
b101111 N
b0 ;
b0 W
b11011011 *
b11011011 >
b11011011 H
b1011111 J
b1100000 I
b101100011111 1
b101100011111 )
b100101 E
b1 F
b100100 D
b11010000 L
b1001101111 K
b0 9
b0 X
b0 3
b0 7
b0 T
b101100011111 &
b11011011 P
b100110011 G
b110011 Q
b101 R
b11111011011111 M
b1001010100 O
b100110111111010000 @
b100110111111010000 C
b100 5
1!
#89000
0!
#90000
b101111100000 (
b101111100000 0
b101111111010 /
b101111111010 :
b101001000100 .
b101001000100 V
b101111100000 *
b101111100000 >
b101111100000 H
b101111111010 ;
b101001000100 W
b110111 E
b1100 F
b101011 D
b101010100100 1
b101010100100 )
b110011010000 G
b11010000 Q
b101111 R
b110010100001 M
b101111 O
b11111011011111 P
b101010100100 &
b11011011 3
b11011011 7
b11011011 T
b101111111010 9
b101001000100 X
b101100011111 2
b101100011111 6
b101100011111 S
b100 5
1!
#91000
0!
#92000
b100110000011 /
b100110000011 :
b101111000101 .
b101111000101 V
b110010100001 (
b110010100001 0
b100110000011 ;
b101111000101 W
b110010100001 *
b110010100001 >
b110010100001 H
b110100 1
b110100 )
b101111100000 3
b101111100000 7
b101111100000 T
b1011010000100 9
b1111011000100 X
b101010100100 2
b101010100100 6
b101010100100 S
b110100 &
b110010100001 P
b100 5
1!
#93000
0!
#94000
b110011010101 /
b110011010101 :
b10010100 .
b10010100 V
b110011010101 ;
b10010100 W
b110010100001 3
b110010100001 7
b110010100001 T
b110011010101 9
b1001110010011 X
b110100 2
b110100 6
b110100 S
b100 5
1!
#95000
0!
#96000
b100 5
1!
#97000
0!
#98000
b100 5
1!
#99000
0!
#100000
b100 5
1!
#101000
0!
#102000
b100 5
1!
#103000
0!
#104000
b100 5
1!
#105000
0!
#106000
b0 /
b0 :
b0 .
b0 V
b0 ;
b0 W
b0 E
b0 F
b0 D
b0 -
b0 =
b0 G
b0 Q
b0 R
b0 M
b0 O
b0 B
b0 ?
b0 A
b0 &
b0 3
b0 7
b0 T
b0 9
b0 X
b0 2
b0 6
b0 S
b0 4
b0 *
b0 >
b0 H
b0 ,
b0 +
b0 <
b110000 0
b0 )
b0 (
b0 P
b100 5
1!
b11 %
b11 8
b11 U
1'
#107000
0!
#108000
b11110110 )
b11110110 ,
b100001000111 (
b100001000111 +
b100001000111 <
b11110110 /
b11110110 :
b100001000111 .
b100001000111 V
b0 N
b11110110 ;
b100001000111 W
b0 J
b0 I
b110011001111 -
b110011001111 =
b110111 E
b1100 F
b101011 D
b0 L
b0 K
b110011001111 4
b1011011000 3
b1011011000 7
b1011011000 T
b110111110111 9
b100001000111 X
b101100011111 2
b101100011111 6
b101100011111 S
b110011010000 G
b11010000 Q
b101111 R
b110010100001 M
b101111 O
b0 @
b0 C
b100 5
b101100011111 1
b1011011000 0
1!
b110011001111 "
b101100011111 #
b1011011000 $
0'
#109000
0!
#110000
b0 )
b0 ,
b0 /
b0 :
b110010100001 *
b110010100001 >
b110010100001 H
b0 ;
b0 E
b0 F
b0 D
b0 G
b0 Q
b0 R
b0 M
b0 O
b110010100001 P
b11010100000010101101001 ?
b110011001111 B
b100001000111 A
b1001011101 3
b1001011101 7
b1001011101 T
b110100000001 9
b100001000111 X
b101010100100 2
b101010100100 6
b101010100100 S
b100 5
b101010100100 1
b1001011101 0
1!
b101010100100 #
b1001011101 $
#111000
0!
#112000
b1100100 )
b1100100 ,
b100 (
b100 +
b100 <
b1100100 /
b1100100 :
b100 .
b100 V
b100000100111 N
b1100100 ;
b100 W
b0 *
b0 >
b0 H
b1000001001110 J
b1000010010000 I
b110011111111 -
b110011111111 =
b1101001 L
b110101000000101 K
b110011111111 4
b110000 3
b110000 7
b110000 T
b1100100 9
b100 X
b110100 2
b110100 6
b110100 S
b0 P
b11010100000010101101001 @
b11010100000010101101001 C
b100 5
b110100 1
b110000 0
1!
b110011111111 "
b110100 #
b110000 $
#113000
0!
#114000
b1101 E
b1010 F
b11 D
b101001101001 G
b1101001 Q
b101 R
b1001000010 M
b100000100111 O
b110011111111 B
b11001111111100 ?
b100 A
b100 5
1!
#115000
0!
#116000
b11 N
b1001000010 *
b1001000010 >
b1001000010 H
b111 J
b111 I
b11111100 L
b110011 K
b11110110 &
b1001000010 P
b11001111111100 @
b11001111111100 C
b100 5
1!
#117000
0!
#118000
b11011 E
b1100 F
b1111 D
b110011111100 G
b11111100 Q
b110011 R
b110011111001 M
b11 O
b0 &
b100 5
1!
#119000
0!
#120000
b110011111001 *
b110011111001 >
b110011111001 H
b1100100 &
b110011111001 P
b100 5
1!
#121000
0!
#122000
b100 5
1!
#123000
0!
#124000
b100 5
1!
#125000
0!
#126000
b100 5
1!
#127000
0!
#128000
b100 5
1!
#129000
0!
#130000
b100 5
1!
#131000
0!
#132000
b100 5
1!
