src/NTT/sub.v
module sub(
    input clk,
    input rst,
    input [1:0] mode,
    input[11:0] in1,
    input[11:0] in2,
    output reg [11:0] res
);
`define  NORMAL 2'd0
`define  DIV_2 2'd1
wire [12:0] diff;
reg [12:0] reduce_diff;
assign diff = in1 - in2;
reg [1:0] mode_reg[0:1];
always @(posedge clk or posedge rst) begin
    if(rst) reduce_diff <= 0;
    else begin
        if(diff[12] == 1) begin
            reduce_diff <= diff[11:0] + 12'd3329; 
        end
        else begin
            reduce_diff <= diff;
        end
        if(mode_reg[1] == 2'd1)begin
            if(reduce_diff[0] == 1) res <= reduce_diff[11:1] + 12'd1665;
            else res <= reduce_diff[11:1];
        end
        else res <= reduce_diff[11:0];
    end
end
always@(posedge clk or posedge rst)begin
    if(rst)begin
        mode_reg[0] <= 0;
        mode_reg[1] <= 0;
    end
    else begin
        mode_reg[0] <= mode;
        mode_reg[1] <= mode_reg[0];
    end
end
endmodule

src/NTT/add.v
module add(
    input clk,
    input rst,
    input [1:0] mode,
    input  [11:0] in1,
    input  [11:0] in2,
    output reg [11:0] res
);

wire [12:0] sum;
assign sum = in1 + in2;  // Direct addition, no need for reg
reg [12:0] reduce_sum;
reg [1:0] mode_reg[0:2];
// Reduce sum conditional
always@(posedge clk or posedge rst)begin
    if(rst) reduce_sum <= 0;
    else begin
        if(sum < 13'd3329)begin
            reduce_sum <= sum;
        end
        else begin
            reduce_sum <= sum[11:0] - 12'd3329;
        end
        if(mode_reg[1] == 2'd1)begin
            if(reduce_sum[0] == 1) res <= reduce_sum[11:1] + 12'd1665;
            else res <= reduce_sum[11:1];
        end
        else res <= reduce_sum[11:0];
    end
end

always@(posedge clk or posedge rst)begin
    if(rst)begin
        mode_reg[0] <= 0;
        mode_reg[1] <= 0;
        mode_reg[2] <= 0;
    end
    else begin
        mode_reg[0] <= mode;
        mode_reg[1] <= mode_reg[0];
    end
end
endmodule

layout/reduce.v
module reduce (
    input clk,
    input rst,
    input [23:0] c,
    output [11:0] r
);

// segment 1
// Calculate Q'1 (Q_1) with low-complexity division by 13.
wire [7:0] c0;
wire [15:0] c1;
wire [13:0] d_1;
wire [13:0] d1_sum;
wire [12:0] Q_1;
assign c0 = c[7:0];
assign c1 = c[23:8];
assign d_1 = c1[15:3] + c1[15:5]; 
assign d1_sum = d_1 - d_1[13:6];
assign Q_1 = d1_sum[13:1];

// stage 1 registers
reg [7:0] c0_reg;
reg [5:0] c1_reg;
reg [12:0] Q_1_reg;
always @(posedge clk or posedge rst) begin
    if(rst) begin
        Q_1_reg <= 0;
        c1_reg <= 0;
        c0_reg <= 0;
    end
    else begin
        Q_1_reg <= Q_1;
        c1_reg <= c1[5:0];
        c0_reg <= c0;
    end
end

// segment 2
// Calculate r'1 (r_1) ~= c1 mod13 with a short width addition tree.
wire [5:0] s_1;
wire [5:0] s_2;
wire [5:0] r_1;
wire [13:0] r1c0;
assign s_1[5:3] = c1_reg[5:3] - Q_1_reg[2:0];
assign s_1[2:0] = c1_reg[2:0];
assign s_2[5:2] = Q_1_reg[5:2] + Q_1_reg[3:0];
assign s_2[1:0] = Q_1_reg[1:0];
assign r_1 = s_1 - s_2;
assign r1c0 = {r_1, c0_reg};

// segment 3
// Obtain raw remander R and calculate r = R mod 3329.
wire [13:0] R;
reg [13:0] R_reg;
assign R = r1c0 - Q_1_reg;
always @(posedge clk or posedge rst) begin
    if(rst) R_reg = 0;
    else R_reg <= R;
end
assign r = R_reg[13] | (R_reg[12:0] >= 13'd3329) ? 
                       (R_reg[11:0] + (R_reg[13] ? 12'd3329 : -12'd3329))
                     : R_reg[11:0];

    
endmodule

src/NTT/mult.v
`include "reduce.v"

module mult(
    input clk,
    input rst,
    input [11:0] in1,
    input [11:0]in2,
    output [11:0] res
);
    reg [11:0] reg1;
    reg [11:0] reg2;
    reg [23:0] dsp_reg[0:3];
    integer i;
    always @(posedge clk or posedge rst)
    begin
        if(rst)
        begin
            reg1 <= 0;
            reg2 <= 0;
        end
        else
        begin
            reg1 <= in1;
            reg2 <= in2;
        end
    end
    wire [23:0] product;
    assign product = reg1*reg2;
    reg [23:0] product_reg;
    always @(posedge clk or posedge rst)begin
        if(rst)begin
            for(i = 0; i < 4; i++)begin
                dsp_reg[i] <= 0;
            end
        end
        else begin
            dsp_reg[0] <= product;
            for(i = 1; i < 3; i++)begin
                dsp_reg[i] <= dsp_reg[i-1];
            end
        end
        
    end
    reduce mod(clk, rst, dsp_reg[2], res);
endmodule

src/NTT/butterfly_core.v
`timescale 1ns / 1ps
 `include "add.v"
 `include "sub.v"
 `include "mult.v"

module butterfly_core(
    input clk,
    input rst,
    input [11:0] in_1,
    input [11:0] in_2,
    input [11:0] coef,
    input [1:0] mode,
    output [11:0] out_1,
    output [11:0] out_2
    );

/*
mode 0: NTT & mul_stage_2 (mul reduce -> add sub, total 5 delay)
mode 1: INVNTT (add sub -> mul reduce, total 5 delay)
mode 2: Point Wise Multiply (4 delay)
*/
`define NTT 2'd0
`define INTT 2'd1
`define MULT 2'd2
`define ADDSUB 2'd3

// mult & reduce
wire [11:0] mult_in_1;
wire [11:0] mult_in_2;
wire [11:0] mult_coef_in;
wire [11:0] mult_out_1;
wire [11:0] mult_out_2;
reg [11:0] mult_in_1_reg [0:5]; // use for timing output (delay 4 circles)
integer i;
mult multiply (
    .clk(clk),
    .rst(rst),
    .in1(mult_in_2),
    .in2(mult_coef_in),
    .res(mult_out_2)
);
always @(posedge clk or posedge rst) begin
    if (rst)begin
        for(i = 0; i < 6; i++)begin
            mult_in_1_reg[i] <= 0;
        end
    end
    else begin
        mult_in_1_reg[0] <= mult_in_1;
        for(i = 1; i < 6; i++)begin
            mult_in_1_reg[i] <= mult_in_1_reg[i-1];
        end
    end

end
assign mult_out_1 = mult_in_1_reg[5];

// add & sub
wire [11:0] addsub_in_1;
wire [11:0] addsub_in_2;
wire [11:0] addsub_out_1;
wire [11:0] addsub_out_2;
reg [11:0]  addsub_in_1_reg;
reg [11:0]  addsub_in_2_reg;
add addition (
    .clk(clk),
    .rst(rst),
    .mode(mode),
    .in1(addsub_in_1_reg),
    .in2(addsub_in_2_reg),
    .res(addsub_out_1)
);
sub subtraction (
    .clk(clk),
    .rst(rst),
    .mode(mode),
    .in1(addsub_in_1_reg),
    .in2(addsub_in_2_reg),
    .res(addsub_out_2)
);

always @(posedge clk or posedge rst) begin
    if(rst) begin
        addsub_in_1_reg <= 0;
        addsub_in_2_reg <= 0;
    end
    else begin
        addsub_in_1_reg <= addsub_in_1;
        addsub_in_2_reg <= addsub_in_2;
    end
end

// input select multiplexers
reg [11:0] mult_coef_in_reg[0:2];
always @(posedge clk or posedge rst) begin
    if(rst)begin
        mult_coef_in_reg[0] <= 0;
        mult_coef_in_reg[1] <= 0;
        mult_coef_in_reg[2] <= 0;
    end
    else begin
        mult_coef_in_reg[0] <= coef;
        mult_coef_in_reg[1] <= mult_coef_in_reg[0];
        mult_coef_in_reg[2] <= mult_coef_in_reg[1];
    end
end
assign mult_in_1 = mode == `INTT || mode == `ADDSUB? addsub_out_1 : in_1;
assign mult_in_2 = mode == `INTT || mode == `ADDSUB? addsub_out_2 : in_2;
assign mult_coef_in = mode == `INTT || mode == `ADDSUB? mult_coef_in_reg[2] : coef;
assign addsub_in_1 = mode == `INTT || mode == `ADDSUB? in_1 : mult_out_1;
assign addsub_in_2 = mode == `INTT || mode == `ADDSUB? in_2 : mult_out_2;

// output select multiplexers
assign out_1 = mode == `NTT || mode == `ADDSUB? addsub_out_1 : mult_out_1;
assign out_2 = mode == `NTT || mode == `ADDSUB? addsub_out_2 : mult_out_2;

endmodule

src/NTT/buterfly_tb.v
`timescale 1us/1us
`include "butterfly_core.v"

module bu_tb;
reg clk;
reg rst;
reg [1:0] mode; // 0:NTT, 1:INVNTT, 2:MULT, 3:ADDSUB
reg [11:0] in_1;
reg [11:0] in_2;
reg [11:0] coef;
wire [11:0] out_1;
wire [11:0] out_2;
butterfly_core BU(
    .clk(clk),
    .rst(rst),
    .in_1(in_1),
    .in_2(in_2),
    .coef(coef),
    .mode(mode),
    .out_1(out_1),
    .out_2(out_2)
    );
initial begin
    $dumpfile("bu_tb.vcd");
    $dumpvars(0, BU);
    #0
    rst = 1;
    mode = 0; // 0:NTT, 1:INVNTT, 2:MULT, 3:ADDSUB
    #10
    rst = 0;
    mode = 0;
    in_1 = 12'd123;
    in_2 = 12'd345;
    coef = 12'd50;
    #2
    in_1 = 12'd0;
    in_2 = 12'd345;
    coef = 12'd50;
    #2
    in_1 = 12'd50;
    in_2 = 12'd3328;
    coef = 12'd2;
    #30
    rst = 1;
    mode = 1; // 0:NTT, 1:INVNTT, 2:MULT, 3:ADDSUB
    #2
    rst = 0;
    mode = 1;
    in_2 = 12'd728;
    in_1 = 12'd2847;
    coef = 12'd3279;
    #2
    in_2 = 12'd605;
    in_1 = 12'd2724;
    coef = 12'd3279;
    #2
    in_2 = 12'd48;
    in_1 = 12'd52;
    coef = 12'd3327;
    #30
    rst = 1;
    mode = 2; // 0:NTT, 1:INVNTT, 2:MULT, 3:ADDSUB
    #2
    rst = 0;
    mode = 2;
    in_2 = 12'd728;
    in_1 = 12'd2847;
    coef = 12'd3279;
    #2
    in_2 = 12'd605;
    in_1 = 12'd2724;
    coef = 12'd3279;
    #2
    in_2 = 12'd48;
    in_1 = 12'd52;
    coef = 12'd3327;
    #20 
    rst = 1;
    mode = 3; // 0:NTT, 1:INVNTT, 2:MULT, 3:ADDSUB
    #2
    rst = 0;
    mode = 3;
    in_2 = 12'd728;
    in_1 = 12'd2847;
    coef = 12'd3279;
    #2
    in_2 = 12'd605;
    in_1 = 12'd2724;
    coef = 12'd3279;
    #2
    in_2 = 12'd48;
    in_1 = 12'd52;
    coef = 12'd3327;
    #20
    $finish;
end
initial begin
    clk = 1;
    forever begin
        #1 clk = ~clk;
    end
end
endmodule

src/NTT/bu_tb.vcd
$date
	Sat Feb 15 22:02:38 2025
$end
$version
	Icarus Verilog
$end
$timescale
	1ps
$end
$scope module bu_tb $end
$scope module BU $end
$var wire 1 ! clk $end
$var wire 12 " coef [11:0] $end
$var wire 12 # in_1 [11:0] $end
$var wire 12 $ in_2 [11:0] $end
$var wire 2 % mode [1:0] $end
$var wire 12 & mult_out_1 [11:0] $end
$var wire 1 ' rst $end
$var wire 12 ( out_2 [11:0] $end
$var wire 12 ) out_1 [11:0] $end
$var wire 12 * mult_out_2 [11:0] $end
$var wire 12 + mult_in_2 [11:0] $end
$var wire 12 , mult_in_1 [11:0] $end
$var wire 12 - mult_coef_in [11:0] $end
$var wire 12 . addsub_out_2 [11:0] $end
$var wire 12 / addsub_out_1 [11:0] $end
$var wire 12 0 addsub_in_2 [11:0] $end
$var wire 12 1 addsub_in_1 [11:0] $end
$var reg 12 2 addsub_in_1_reg [11:0] $end
$var reg 12 3 addsub_in_2_reg [11:0] $end
$var integer 32 4 i [31:0] $end
$scope module addition $end
$var wire 1 ! clk $end
$var wire 12 5 in1 [11:0] $end
$var wire 12 6 in2 [11:0] $end
$var wire 2 7 mode [1:0] $end
$var wire 1 ' rst $end
$var wire 13 8 sum [12:0] $end
$var reg 13 9 reduce_sum [12:0] $end
$var reg 12 : res [11:0] $end
$upscope $end
$scope module multiply $end
$var wire 1 ! clk $end
$var wire 12 ; in1 [11:0] $end
$var wire 12 < in2 [11:0] $end
$var wire 1 ' rst $end
$var wire 12 = res [11:0] $end
$var wire 24 > product [23:0] $end
$var reg 12 ? reg1 [11:0] $end
$var reg 12 @ reg2 [11:0] $end
$var integer 32 A i [31:0] $end
$scope module mod $end
$var wire 24 B c [23:0] $end
$var wire 1 ! clk $end
$var wire 1 ' rst $end
$var wire 6 C s_2 [5:0] $end
$var wire 6 D s_1 [5:0] $end
$var wire 6 E r_1 [5:0] $end
$var wire 14 F r1c0 [13:0] $end
$var wire 12 G r [11:0] $end
$var wire 14 H d_1 [13:0] $end
$var wire 14 I d1_sum [13:0] $end
$var wire 16 J c1 [15:0] $end
$var wire 8 K c0 [7:0] $end
$var wire 14 L R [13:0] $end
$var wire 13 M Q_1 [12:0] $end
$var reg 13 N Q_1_reg [12:0] $end
$var reg 14 O R_reg [13:0] $end
$var reg 8 P c0_reg [7:0] $end
$var reg 6 Q c1_reg [5:0] $end
$upscope $end
$upscope $end
$scope module subtraction $end
$var wire 1 ! clk $end
$var wire 12 R in1 [11:0] $end
$var wire 12 S in2 [11:0] $end
$var wire 2 T mode [1:0] $end
$var wire 1 ' rst $end
$var wire 13 U diff [12:0] $end
$var reg 13 V reduce_diff [12:0] $end
$var reg 12 W res [11:0] $end
$upscope $end
$upscope $end
$upscope $end
$enddefinitions $end
$comment Show the parameter values. $end
$dumpall
$end
#0
$dumpvars
bx W
b0 V
b0 U
b0 T
b0 S
b0 R
b0 Q
b0 P
bx O
b0 N
b0 M
b0 L
b0 K
b0 J
b0 I
b0 H
bx G
b0 F
b0 E
b0 D
b0 C
b0 B
b100 A
b0 @
b0 ?
b0 >
bx =
bx <
bx ;
bx :
b0 9
b0 8
b0 7
b0 6
b0 5
b110 4
b0 3
b0 2
b0 1
bx 0
bx /
bx .
bx -
bx ,
bx +
bx *
bx )
bx (
1'
b0 &
b0 %
bx $
bx #
bx "
1!
$end
#1000
0!
#2000
b0 0
b0 *
b0 =
b0 G
b0 O
b100 A
b110 4
1!
#3000
0!
#4000
b110 4
b100 A
1!
#5000
0!
#6000
b100 A
b110 4
1!
#7000
0!
#8000
b110 4
b100 A
1!
#9000
0!
#10000
b0 )
b0 (
b100001101100010 >
b110010 @
b101011001 ?
b0 /
b0 :
b0 .
b0 W
b11 A
b110 4
b110010 -
b110010 <
b101011001 +
b101011001 ;
b1111011 ,
1!
b110010 "
b101011001 $
b1111011 #
0'
#11000
0!
#12000
b110 4
b11 A
b0 ,
1!
b0 #
#13000
0!
#14000
b10 @
b1101000000000 >
b110100000000 ?
b11 A
b110 4
b10 -
b10 <
b110100000000 +
b110100000000 ;
b110010 ,
1!
b10 "
b110100000000 $
b110010 #
#15000
0!
#16000
b101 M
b1010 I
b1010 H
b1100010 K
b1000011 J
b100001101100010 B
b110 4
b11 A
1!
#17000
0!
#18000
b11011 D
b10 E
b11001 C
b1001100010 F
b1100010 P
b11 Q
b1001011101 L
b101 N
b11 A
b110 4
1!
#19000
0!
#20000
b1 M
b1001011101 0
b11 I
b11 H
b1001011101 *
b1001011101 =
b1001011101 G
b1111011 1
b0 K
b11010 J
b1111011 &
b1101000000000 B
b1001011101 O
b110 4
b11 A
1!
#21000
0!
#22000
b10010 D
b1101 E
b101 C
b0 1
b110100000000 F
b0 P
b11010 Q
b110011111111 L
b1 N
b0 &
b1001011101 3
b1001011101 6
b1001011101 S
b1011011000 8
b1111000011110 U
b1111011 2
b1111011 5
b1111011 R
b11 A
b110 4
1!
#23000
0!
#24000
b110011111111 0
b110011111111 *
b110011111111 =
b110011111111 G
b110010 1
b1001011101 8
b1110110100011 U
b0 2
b0 5
b0 R
b110010 &
b1101100011111 V
b1011011000 9
b110011111111 O
b110 4
b11 A
1!
#25000
0!
#26000
b1011011000 )
b101100011111 (
b1011011000 /
b1011011000 :
b1001011101 9
b101100011111 .
b101100011111 W
b1101010100100 V
b110011111111 3
b110011111111 6
b110011111111 S
b110100110001 8
b1001100110011 U
b110010 2
b110010 5
b110010 R
b11 A
b110 4
1!
#27000
0!
#28000
b101010100100 (
b1001011101 )
b101010100100 .
b101010100100 W
b1000000110100 V
b1001011101 /
b1001011101 :
b110000 9
b110 4
b11 A
1!
#29000
0!
#30000
b110000 )
b110100 (
b110000 /
b110000 :
b110100 .
b110100 W
b11 A
b110 4
1!
#31000
0!
#32000
b110 4
b11 A
1!
#33000
0!
#34000
b11 A
b110 4
1!
#35000
0!
#36000
b110 4
b11 A
1!
#37000
0!
#38000
b11 A
b110 4
1!
#39000
0!
#40000
b110 4
b11 A
1!
#41000
0!
#42000
b11 A
b110 4
1!
#43000
0!
#44000
b0 M
b0 I
b0 H
b0 -
b0 <
b0 J
b0 D
b0 F
b0 E
b0 C
b0 3
b0 6
b0 S
b0 8
b0 U
b0 2
b0 5
b0 R
b0 &
b0 V
b0 9
b0 B
b0 @
b0 >
b0 ?
b0 Q
b0 L
b0 N
b0 *
b0 =
b0 G
b110000 ,
b110100 +
b110100 ;
b110100000000 0
b0 )
b0 (
b110 4
b100 A
b0 O
1!
b1 %
b1 7
b1 T
1'
#45000
0!
#46000
b0 ,
b0 +
b0 ;
b110100 ?
b0 /
b0 :
b0 .
b0 W
b1011011000 3
b1011011000 6
b1011011000 S
b110111110111 8
b100001000111 U
b101100011111 2
b101100011111 5
b101100011111 R
b11 A
b110 4
b101100011111 1
b1011011000 0
1!
b110011001111 "
b101100011111 #
b1011011000 $
0'
#47000
0!
#48000
b1001011101 3
b1001011101 6
b1001011101 S
b110100000001 8
b100001000111 U
b101010100100 2
b101010100100 5
b101010100100 R
b100001000111 V
b11110110 9
b0 ?
b110 4
b11 A
b101010100100 1
b1001011101 0
1!
b101010100100 #
b1001011101 $
#49000
0!
#50000
b1111011 ,
b101010100100 +
b101010100100 ;
b110011001111 -
b110011001111 <
b1111011 /
b1111011 :
b0 9
b101010100100 .
b101010100100 W
b110000 3
b110000 6
b110000 S
b1100100 8
b100 U
b110100 2
b110100 5
b110100 R
b11 A
b110 4
b110100 1
b110000 0
1!
b110011111111 "
b110100 #
b110000 $
#51000
0!
#52000
b0 ,
b100 V
b0 /
b0 :
b1100100 9
b100010000100101010011100 >
b110011001111 @
b101010100100 ?
b110 4
b11 A
1!
#53000
0!
#54000
b110010 ,
b10 +
b10 ;
b110011111111 -
b110011111111 <
b110010 /
b110010 :
b10 .
b10 W
b11 A
b110 4
1!
#55000
0!
#56000
b110000 )
b110000 &
b110011111111 @
b1100111111110 >
b10 ?
b110 4
b11 A
1!
#57000
0!
#58000
b101001111011 M
b1010011110110 I
b1010101001011 H
b10011100 K
b1000100001001010 J
b0 )
b100010000100101010011100 B
b0 &
b11 A
b110 4
1!
#59000
0!
#60000
b110010 D
b1011 E
b100111 C
b101110011100 F
b10011100 P
b1010 Q
b100100001 L
b101001111011 N
b110 4
b11 A
1!
#61000
0!
#62000
b100100001 (
b1 M
b100100001 *
b100100001 =
b100100001 G
b11 I
b11 H
b11111110 K
b11001 J
b1111011 )
b100100001 O
b1100111111110 B
b1111011 &
b11 A
b110 4
1!
#63000
0!
#64000
b0 )
b10001 D
b1100 E
b101 C
b0 &
b110011111110 F
b11111110 P
b11001 Q
b110011111101 L
b1 N
b110 4
b11 A
1!
#65000
0!
#66000
b110011111101 (
b110011111101 *
b110011111101 =
b110011111101 G
b110010 )
b110011111101 O
b110010 &
b11 A
b110 4
1!
#67000
0!
#68000
b110 4
b11 A
1!
#69000
0!
#70000
b11 A
b110 4
1!
#71000
0!
#72000
b110 4
b11 A
1!
#73000
0!
#74000
b11 A
b110 4
1!
#75000
0!
#76000
b110 4
b11 A
1!
#77000
0!
#78000
b11 A
b110 4
1!
#79000
0!
#80000
b0 M
b0 I
b0 H
b0 )
b0 K
b0 J
b0 D
b0 E
b0 C
b0 3
b0 6
b0 S
b0 8
b0 U
b0 2
b0 5
b0 R
b0 &
b0 V
b0 9
b0 B
b0 @
b0 >
b0 ?
b0 F
b0 P
b0 Q
b0 L
b0 N
b0 (
b0 *
b0 =
b0 G
b110100 ,
b110000 +
b110000 ;
b0 1
b0 0
b110 4
b100 A
b0 O
1!
b10 %
b10 7
b10 T
1'
#81000
0!
#82000
b1001000110110010101000 >
b110011001111 @
b1011011000 ?
b0 /
b0 :
b0 .
b0 W
b11 A
b110 4
b110011001111 -
b110011001111 <
b101100011111 ,
b1011011000 +
b1011011000 ;
1!
b110011001111 "
b101100011111 #
b1011011000 $
0'
#83000
0!
#84000
b111100100010100110011 >
b1001011101 ?
b110 4
b11 A
b101010100100 ,
b1001011101 +
b1001011101 ;
1!
b101010100100 #
b1001011101 $
#85000
0!
#86000
b110011111111 @
b100110111111010000 >
b110000 ?
b11 A
b110 4
b110011111111 -
b110011111111 <
b110100 ,
b110000 +
b110000 ;
1!
b110011111111 "
b110100 #
b110000 $
#87000
0!
#88000
b1011001101 M
b10110011010 I
b10110110000 H
b10101000 K
b10010001101100 J
b1001000110110010101000 B
b110 4
b11 A
1!
#89000
0!
#90000
b1001010100 M
b10010101000 I
b10010111010 H
b100 D
b11 E
b1 C
b110011 K
b1111001000101 J
b1110101000 F
b10101000 P
b101100 Q
b11011011 L
b1011001101 N
b111100100010100110011 B
b11 A
b110 4
1!
#91000
0!
#92000
b101111 M
b11011011 (
b11011011 0
b1011111 I
b1100000 H
b11011011 *
b11011011 =
b11011011 G
b101100011111 1
b101100011111 )
b11010000 K
b1001101111 J
b100101 D
b1 E
b100100 C
b101100011111 &
b100110111111010000 B
b11011011 O
b100110011 F
b110011 P
b101 Q
b11111011011111 L
b1001010100 N
b110 4
b11 A
1!
#93000
0!
#94000
b101111100000 (
b101111100000 0
b101111100000 *
b101111100000 =
b101111100000 G
b110111 D
b1100 E
b101011 C
b101010100100 1
b101010100100 )
b110011010000 F
b11010000 P
b101111 Q
b110010100001 L
b101111 N
b11111011011111 O
b101010100100 &
b11011011 3
b11011011 6
b11011011 S
b101111111010 8
b101001000100 U
b101100011111 2
b101100011111 5
b101100011111 R
b11 A
b110 4
1!
#95000
0!
#96000
b110010100001 (
b110010100001 0
b110010100001 *
b110010100001 =
b110010100001 G
b110100 1
b110100 )
b101111100000 3
b101111100000 6
b101111100000 S
b1011010000100 8
b1111011000100 U
b101010100100 2
b101010100100 5
b101010100100 R
b110100 &
b101001000100 V
b101111111010 9
b110010100001 O
b110 4
b11 A
1!
#97000
0!
#98000
b101111111010 /
b101111111010 :
b1100110000011 9
b101001000100 .
b101001000100 W
b1101111000101 V
b110010100001 3
b110010100001 6
b110010100001 S
b110011010101 8
b1001110010011 U
b110100 2
b110100 5
b110100 R
b11 A
b110 4
1!
#99000
0!
#100000
b101111000101 .
b101111000101 W
b1000010010100 V
b100110000011 /
b100110000011 :
b110011010101 9
b110 4
b11 A
1!
#101000
0!
#102000
b110011010101 /
b110011010101 :
b10010100 .
b10010100 W
b11 A
b110 4
1!
#103000
0!
#104000
b110 4
b11 A
1!
#105000
0!
#106000
b0 M
b0 I
b0 H
b0 D
b0 E
b0 C
b0 K
b0 J
b0 -
b0 <
b0 F
b0 P
b0 Q
b0 L
b0 N
b0 @
b0 >
b0 ?
b0 B
b0 9
b0 V
b0 &
b0 3
b0 6
b0 S
b0 8
b0 U
b0 2
b0 5
b0 R
b0 *
b0 =
b0 G
b110011010101 ,
b10010100 +
b10010100 ;
b110000 0
b110011010101 )
b10010100 (
b0 O
b100 A
b110 4
1!
b11 %
b11 7
b11 T
1'
#107000
0!
#108000
b0 (
b0 +
b0 ;
b0 )
b0 ,
b1011011000 3
b1011011000 6
b1011011000 S
b110111110111 8
b100001000111 U
b101100011111 2
b101100011111 5
b101100011111 R
b0 .
b0 W
b0 /
b0 :
b10010100 ?
b110 4
b11 A
b101100011111 1
b1011011000 0
1!
b110011001111 "
b101100011111 #
b1011011000 $
0'
#109000
0!
#110000
b0 ?
b11110110 9
b100001000111 V
b1001011101 3
b1001011101 6
b1001011101 S
b110100000001 8
b100001000111 U
b101010100100 2
b101010100100 5
b101010100100 R
b11 A
b110 4
b101010100100 1
b1001011101 0
1!
b101010100100 #
b1001011101 $
#111000
0!
#112000
b110011001111 -
b110011001111 <
b100001000111 (
b100001000111 +
b100001000111 ;
b11110110 )
b11110110 ,
b110000 3
b110000 6
b110000 S
b1100100 8
b100 U
b110100 2
b110100 5
b110100 R
b100001000111 .
b100001000111 W
b11110110 /
b11110110 :
b0 9
b110 4
b11 A
b110100 1
b110000 0
1!
b110011111111 "
b110100 #
b110000 $
#113000
0!
#114000
b0 )
b0 ,
b11010100000010101101001 >
b110011001111 @
b100001000111 ?
b0 /
b0 :
b1100100 9
b100 V
b11 A
b110 4
1!
#115000
0!
#116000
b110011111111 -
b110011111111 <
b100 (
b100 +
b100 ;
b1100100 )
b1100100 ,
b100 .
b100 W
b1100100 /
b1100100 :
b110 4
b11 A
1!
#117000
0!
#118000
b110011111111 @
b11001111111100 >
b100 ?
b110011010101 &
b11 A
b110 4
1!
#119000
0!
#120000
b100000100111 M
b1000001001110 I
b1000010010000 H
b1101001 K
b110101000000101 J
b0 &
b11010100000010101101001 B
b110 4
b11 A
1!
#121000
0!
#122000
b1101 D
b1010 E
b11 C
b101001101001 F
b1101001 P
b101 Q
b1001000010 L
b100000100111 N
b11 A
b110 4
1!
#123000
0!
#124000
b11 M
b111 I
b111 H
b1001000010 *
b1001000010 =
b1001000010 G
b11111100 K
b110011 J
b11110110 &
b11001111111100 B
b1001000010 O
b110 4
b11 A
1!
#125000
0!
#126000
b11011 D
b1100 E
b1111 C
b110011111100 F
b11111100 P
b110011 Q
b110011111001 L
b11 N
b0 &
b11 A
b110 4
1!
#127000
0!
#128000
b110011111001 *
b110011111001 =
b110011111001 G
b1100100 &
b110011111001 O
b110 4
b11 A
1!
#129000
0!
#130000
b11 A
b110 4
1!
#131000
0!
#132000
b110 4
b11 A
1!
