layout/reduce.v
module reduce (
    input clk,
    input rst,
    input [23:0] c,
    output [11:0] r
);

// segment 1
// Calculate Q'1 (Q_1) with low-complexity division by 13.
wire [7:0] c0;
wire [15:0] c1;
wire [13:0] d_1;
wire [13:0] d1_sum;
wire [12:0] Q_1;
assign c0 = c[7:0];
assign c1 = c[23:8];
assign d_1 = c1[15:3] + c1[15:5]; 
assign d1_sum = d_1 - d_1[13:6];
assign Q_1 = d1_sum[13:1];

// stage 1 registers
reg [7:0] c0_reg;
reg [5:0] c1_reg;
reg [12:0] Q_1_reg;
always @(posedge clk or posedge rst) begin
    if(rst) begin
        Q_1_reg <= 0;
        c1_reg <= 0;
        c0_reg <= 0;
    end
    else begin
        Q_1_reg <= Q_1;
        c1_reg <= c1[5:0];
        c0_reg <= c0;
    end
end

// segment 2
// Calculate r'1 (r_1) ~= c1 mod13 with a short width addition tree.
wire [5:0] s_1;
wire [5:0] s_2;
wire [5:0] r_1;
wire [13:0] r1c0;
assign s_1[5:3] = c1_reg[5:3] - Q_1_reg[2:0];
assign s_1[2:0] = c1_reg[2:0];
assign s_2[5:2] = Q_1_reg[5:2] + Q_1_reg[3:0];
assign s_2[1:0] = Q_1_reg[1:0];
assign r_1 = s_1 - s_2;
assign r1c0 = {r_1, c0_reg};

// segment 3
// Obtain raw remander R and calculate r = R mod 3329.
wire [13:0] R;
reg [13:0] R_reg;
assign R = r1c0 - Q_1_reg;
always @(posedge clk or posedge rst) begin
    if(rst) R_reg = 0;
    else R_reg <= R;
end
assign r = R_reg[13] | (R_reg[12:0] >= 13'd3329) ? 
                       (R_reg[11:0] + (R_reg[13] ? 12'd3329 : -12'd3329))
                     : R_reg[11:0];

    
endmodule

src/NTT/mult.v
`include "reduce.v"

module mult(
    input clk,
    input rst,
    input [11:0] in1,
    input [11:0]in2,
    output [11:0] res
);
    reg [11:0] reg1;
    reg [11:0] reg2;
    reg [23:0] dsp_reg[0:3];
    integer i;
    always @(posedge clk or posedge rst)
    begin
        if(rst)
        begin
            reg1 <= 0;
            reg2 <= 0;
        end
        else
        begin
            reg1 <= in1;
            reg2 <= in2;
        end
    end
    wire [23:0] product;
    assign product = reg1*reg2;
    reg [23:0] product_reg;
    always @(posedge clk or posedge rst)begin
        if(rst)begin
            for(i = 0; i < 4; i++)begin
                dsp_reg[i] <= 0;
            end
        end
        else begin
            dsp_reg[0] <= product;
            for(i = 1; i < 3; i++)begin
                dsp_reg[i] <= dsp_reg[i-1];
            end
        end
        
    end
    reduce mod(clk, rst, dsp_reg[2], res);
endmodule

testcase/mult_tb.v
`include "mult.v"
`timescale 1ns/1ns
module mult_tb;
wire [11:0]out;
reg clk;
reg rst;
reg [11:0]in1;
reg [11:0]in2;
mult mult_ut(out, in1, in2, clk, rst);
initial begin
    $dumpfile("mult_tb.vcd");
    $dumpvars(0, mult_tb);
    rst = 1;
    #5
    rst = 0;
    in1 = 10;
    in2 = 300;
    #20
    in1 = 3300;
    in2 = 3290;
    #20
    in1 = 3000;
    in2 = 3111;
    #20
    in1 = 200;
    in2 = 10;
    #5
    rst = 1;
    #20
    $finish;
end
initial begin
    clk = 0;
    forever begin
        #2 clk = ~clk;
    end
end
endmodule

src/NTT/mult_tb.vcd
$date
	Sun Feb 16 15:14:43 2025
$end
$version
	Icarus Verilog
$end
$timescale
	1ns
$end
$scope module mult_tb $end
$var wire 12 ! out [11:0] $end
$var reg 1 " clk $end
$var reg 12 # in1 [11:0] $end
$var reg 12 $ in2 [11:0] $end
$var reg 1 % rst $end
$scope module mult_ut $end
$var wire 1 " clk $end
$var wire 12 & in1 [11:0] $end
$var wire 12 ' in2 [11:0] $end
$var wire 1 % rst $end
$var wire 12 ( res [11:0] $end
$var wire 24 ) product [23:0] $end
$var reg 12 * reg1 [11:0] $end
$var reg 12 + reg2 [11:0] $end
$var integer 32 , i [31:0] $end
$scope module mod $end
$var wire 24 - c [23:0] $end
$var wire 1 " clk $end
$var wire 1 % rst $end
$var wire 6 . s_2 [5:0] $end
$var wire 6 / s_1 [5:0] $end
$var wire 6 0 r_1 [5:0] $end
$var wire 14 1 r1c0 [13:0] $end
$var wire 12 2 r [11:0] $end
$var wire 14 3 d_1 [13:0] $end
$var wire 14 4 d1_sum [13:0] $end
$var wire 16 5 c1 [15:0] $end
$var wire 8 6 c0 [7:0] $end
$var wire 14 7 R [13:0] $end
$var wire 13 8 Q_1 [12:0] $end
$var reg 13 9 Q_1_reg [12:0] $end
$var reg 14 : R_reg [13:0] $end
$var reg 8 ; c0_reg [7:0] $end
$var reg 6 < c1_reg [5:0] $end
$upscope $end
$upscope $end
$upscope $end
$enddefinitions $end
$comment Show the parameter values. $end
$dumpall
$end
#0
$dumpvars
b0 <
b0 ;
b0 :
b0 9
b0 8
b0 7
b0 6
b0 5
b0 4
b0 3
b0 2
b0 1
b0 0
b0 /
b0 .
b0 -
b100 ,
b0 +
b0 *
b0 )
b0 (
bx '
bx &
1%
bx $
bx #
0"
b0 !
$end
#2
b100 ,
1"
#4
0"
#5
b100101100 $
b100101100 '
b1010 #
b1010 &
0%
#6
b101110111000 )
b100101100 +
b1010 *
b11 ,
1"
#8
0"
#10
b11 ,
1"
#12
0"
#14
b11 ,
1"
#16
0"
#18
b1 4
b1 3
b10111000 6
b1011 5
b101110111000 -
b11 ,
1"
#20
0"
#22
b1011 0
b1011 /
b101110111000 7
b101110111000 1
b10111000 ;
b1011 <
b11 ,
1"
#24
0"
#25
b110011011010 $
b110011011010 '
b110011100100 #
b110011100100 &
#26
b101110111000 !
b101110111000 (
b101110111000 2
b110011011010 +
b101001011010101000101000 )
b110011100100 *
b101110111000 :
b11 ,
1"
#28
0"
#30
b11 ,
1"
#32
0"
#34
b11 ,
1"
#36
0"
#38
b110010111101 8
b1100101111011 4
b1100111100010 3
b101000 6
b1010010110101010 5
b101001011010101000101000 -
b11 ,
1"
#40
0"
#42
b10 /
b10001 0
b110001 .
b1000100101000 1
b101000 ;
b101010 <
b10001101011 7
b110010111101 9
b11 ,
1"
#44
0"
#45
b110000100111 $
b110000100111 '
b101110111000 #
b101110111000 &
#46
b10001101011 !
b10001101011 (
b10001101011 2
b10001101011 :
b110000100111 +
b100011100110100100001000 )
b101110111000 *
b11 ,
1"
#48
0"
#50
b11 ,
1"
#52
0"
#54
b11 ,
1"
#56
0"
#58
b101011110011 8
b1010111100111 4
b1011001000000 3
b1000 6
b1000111001101001 5
b100011100110100100001000 -
b11 ,
1"
#60
0"
#62
b10001 /
b10010 0
b111111 .
b1001000001000 1
b1000 ;
b101001 <
b11100010101 7
b101011110011 9
b11 ,
1"
#64
0"
#65
b1010 $
b1010 '
b11001000 #
b11001000 &
#66
b11100010101 !
b11100010101 (
b11100010101 2
b1010 +
b11111010000 )
b11001000 *
b11100010101 :
b11 ,
1"
#68
0"
#70
b0 8
b0 4
b0 3
b0 /
b0 0
b0 .
b0 6
b0 5
b0 1
b0 ;
b0 <
b0 7
b0 9
b0 +
b0 )
b0 *
b0 -
b0 !
b0 (
b0 2
b0 :
b100 ,
1"
1%
#72
0"
#74
b100 ,
1"
#76
0"
#78
b100 ,
1"
#80
0"
#82
b100 ,
1"
#84
0"
#86
b100 ,
1"
#88
0"
#90
b100 ,
1"
